<?xml version="1.0" ?>
<text id="3203" name="Где эта улица, где этот дом?" parent="226">
	<tags>
		<tag>url:http://www.chaskor.ru/news/gde_eta_ulitsa_gde_etot_dom_10424</tag>
		<tag>Дата:18/09</tag>
		<tag>Тема:ЧасКор:Экономика/Недвижимость</tag>
		<tag>Тема:ЧасКор:Экономика</tag>
		<tag>Год:2009</tag>
	</tags>
	<paragraphs>
		<paragraph id="26240">
			<sentence id="76500">
				<source>Где эта улица, где этот дом?</source>
				<tokens>
					<token id="1375037" text="Где">
						<tfr rev_id="3025725" t="Где">
							<v>
								<l id="67984" t="где">
									<g v="ADVB"/>
									<g v="Ques"/>
								</l>
							</v>
							<v>
								<l id="388669" t="где">
									<g v="CONJ"/>
								</l>
							</v>
						</tfr>
					</token>
					<token id="1375038" text="эта">
						<tfr rev_id="4437432" t="эта">
							<v>
								<l id="386581" t="этот">
									<g v="ADJF"/>
									<g v="Subx"/>
									<g v="Apro"/>
									<g v="Anph"/>
									<g v="femn"/>
									<g v="sing"/>
									<g v="nomn"/>
								</l>
							</v>
						</tfr>
					</token>
					<token id="1375039" text="улица">
						<tfr rev_id="3025727" t="улица">
							<v>
								<l id="356890" t="улица">
									<g v="NOUN"/>
									<g v="inan"/>
									<g v="femn"/>
									<g v="sing"/>
									<g v="nomn"/>
								</l>
							</v>
						</tfr>
					</token>
					<token id="1375040" text=",">
						<tfr rev_id="3025728" t=",">
							<v>
								<l id="0" t=",">
									<g v="PNCT"/>
								</l>
							</v>
						</tfr>
					</token>
					<token id="1375041" text="где">
						<tfr rev_id="3025729" t="где">
							<v>
								<l id="67984" t="где">
									<g v="ADVB"/>
									<g v="Ques"/>
								</l>
							</v>
							<v>
								<l id="388669" t="где">
									<g v="CONJ"/>
								</l>
							</v>
						</tfr>
					</token>
					<token id="1375042" text="этот">
						<tfr rev_id="4432546" t="этот">
							<v>
								<l id="386581" t="этот">
									<g v="ADJF"/>
									<g v="Subx"/>
									<g v="Apro"/>
									<g v="Anph"/>
									<g v="masc"/>
									<g v="sing"/>
									<g v="nomn"/>
								</l>
							</v>
							<v>
								<l id="386581" t="этот">
									<g v="ADJF"/>
									<g v="Subx"/>
									<g v="Apro"/>
									<g v="Anph"/>
									<g v="inan"/>
									<g v="masc"/>
									<g v="sing"/>
									<g v="accs"/>
								</l>
							</v>
						</tfr>
					</token>
					<token id="1375043" text="дом">
						<tfr rev_id="4075981" t="дом">
							<v>
								<l id="88152" t="дом">
									<g v="NOUN"/>
									<g v="inan"/>
									<g v="masc"/>
									<g v="sing"/>
									<g v="nomn"/>
								</l>
							</v>
						</tfr>
					</token>
					<token id="1375044" text="?">
						<tfr rev_id="3025732" t="?">
							<v>
								<l id="0" t="?">
									<g v="PNCT"/>
								</l>
							</v>
						</tfr>
					</token>
				</tokens>
			</sentence>
		</paragraph>
		<paragraph id="26241">
			<sentence id="76501">
				<source>Власти Москвы озвучили себестоимость одного квадратного метра жилья в столице.</source>
				<tokens>
					<token id="1375045" text="Власти">
						<tfr rev_id="3822034" t="Власти">
							<v>
								<l id="46816" t="власть">
									<g v="NOUN"/>
									<g v="inan"/>
									<g v="femn"/>
									<g v="plur"/>
									<g v="nomn"/>
								</l>
							</v>
						</tfr>
					</token>
					<token id="1375046" text="Москвы">
						<tfr rev_id="3025734" t="Москвы">
							<v>
								<l id="163901" t="москва">
									<g v="NOUN"/>
									<g v="inan"/>
									<g v="femn"/>
									<g v="Sgtm"/>
									<g v="Geox"/>
									<g v="sing"/>
									<g v="gent"/>
								</l>
							</v>
						</tfr>
					</token>
					<token id="1375047" text="озвучили">
						<tfr rev_id="3025735" t="озвучили">
							<v>
								<l id="204107" t="озвучил">
									<g v="VERB"/>
									<g v="perf"/>
									<g v="tran"/>
									<g v="plur"/>
									<g v="past"/>
									<g v="indc"/>
								</l>
							</v>
						</tfr>
					</token>
					<token id="1375048" text="себестоимость">
						<tfr rev_id="3025736" t="себестоимость">
							<v>
								<l id="317453" t="себестоимость">
									<g v="NOUN"/>
									<g v="inan"/>
									<g v="femn"/>
									<g v="sing"/>
									<g v="nomn"/>
								</l>
							</v>
							<v>
								<l id="317453" t="себестоимость">
									<g v="NOUN"/>
									<g v="inan"/>
									<g v="femn"/>
									<g v="sing"/>
									<g v="accs"/>
								</l>
							</v>
						</tfr>
					</token>
					<token id="1375049" text="одного">
						<tfr rev_id="4371226" t="одного">
							<v>
								<l id="203319" t="один">
									<g v="ADJF"/>
									<g v="Apro"/>
									<g v="Anum"/>
									<g v="masc"/>
									<g v="sing"/>
									<g v="gent"/>
								</l>
							</v>
							<v>
								<l id="203319" t="один">
									<g v="ADJF"/>
									<g v="Apro"/>
									<g v="Anum"/>
									<g v="anim"/>
									<g v="masc"/>
									<g v="sing"/>
									<g v="accs"/>
								</l>
							</v>
						</tfr>
					</token>
					<token id="1375050" text="квадратного">
						<tfr rev_id="4415349" t="квадратного">
							<v>
								<l id="131789" t="квадратный">
									<g v="ADJF"/>
									<g v="Qual"/>
									<g v="masc"/>
									<g v="sing"/>
									<g v="gent"/>
								</l>
							</v>
						</tfr>
					</token>
					<token id="1375051" text="метра">
						<tfr rev_id="4461348" t="метра">
							<v>
								<l id="159295" t="метр">
									<g v="NOUN"/>
									<g v="anim"/>
									<g v="masc"/>
									<g v="sing"/>
									<g v="gent"/>
								</l>
							</v>
							<v>
								<l id="159296" t="метр">
									<g v="NOUN"/>
									<g v="inan"/>
									<g v="masc"/>
									<g v="sing"/>
									<g v="gent"/>
								</l>
							</v>
						</tfr>
					</token>
					<token id="1375052" text="жилья">
						<tfr rev_id="3025740" t="жилья">
							<v>
								<l id="97400" t="жильё">
									<g v="NOUN"/>
									<g v="inan"/>
									<g v="neut"/>
									<g v="Sgtm"/>
									<g v="sing"/>
									<g v="gent"/>
								</l>
							</v>
						</tfr>
					</token>
					<token id="1375053" text="в">
						<tfr rev_id="3025741" t="в">
							<v>
								<l id="37409" t="в">
									<g v="PREP"/>
								</l>
							</v>
						</tfr>
					</token>
					<token id="1375054" text="столице">
						<tfr rev_id="3660947" t="столице">
							<v>
								<l id="336588" t="столица">
									<g v="NOUN"/>
									<g v="inan"/>
									<g v="femn"/>
									<g v="sing"/>
									<g v="loct"/>
								</l>
							</v>
						</tfr>
					</token>
					<token id="1375055" text=".">
						<tfr rev_id="3025743" t=".">
							<v>
								<l id="0" t=".">
									<g v="PNCT"/>
								</l>
							</v>
						</tfr>
					</token>
				</tokens>
			</sentence>
		</paragraph>
		<paragraph id="26242">
			<sentence id="76502">
				<source>Оказывается, себестоимость строительства жилых домов на территории столицы в настоящий момент составляет 40 тыс. рублей за квадратный метр.</source>
				<tokens>
					<token id="1375056" text="Оказывается">
						<tfr rev_id="4213642" t="Оказывается">
							<v>
								<l id="388704" t="оказывается">
									<g v="CONJ"/>
									<g v="Prnt"/>
								</l>
							</v>
						</tfr>
					</token>
					<token id="1375057" text=",">
						<tfr rev_id="3025745" t=",">
							<v>
								<l id="0" t=",">
									<g v="PNCT"/>
								</l>
							</v>
						</tfr>
					</token>
					<token id="1375058" text="себестоимость">
						<tfr rev_id="3859926" t="себестоимость">
							<v>
								<l id="317453" t="себестоимость">
									<g v="NOUN"/>
									<g v="inan"/>
									<g v="femn"/>
									<g v="sing"/>
									<g v="nomn"/>
								</l>
							</v>
						</tfr>
					</token>
					<token id="1375059" text="строительства">
						<tfr rev_id="3025747" t="строительства">
							<v>
								<l id="337671" t="строительство">
									<g v="NOUN"/>
									<g v="inan"/>
									<g v="neut"/>
									<g v="sing"/>
									<g v="gent"/>
								</l>
							</v>
							<v>
								<l id="337671" t="строительство">
									<g v="NOUN"/>
									<g v="inan"/>
									<g v="neut"/>
									<g v="plur"/>
									<g v="nomn"/>
								</l>
							</v>
							<v>
								<l id="337671" t="строительство">
									<g v="NOUN"/>
									<g v="inan"/>
									<g v="neut"/>
									<g v="plur"/>
									<g v="accs"/>
								</l>
							</v>
						</tfr>
					</token>
					<token id="1375060" text="жилых">
						<tfr rev_id="4401286" t="жилых">
							<v>
								<l id="97384" t="жилой">
									<g v="ADJF"/>
									<g v="plur"/>
									<g v="gent"/>
								</l>
							</v>
						</tfr>
					</token>
					<token id="1375061" text="домов">
						<tfr rev_id="3025749" t="домов">
							<v>
								<l id="88152" t="дом">
									<g v="NOUN"/>
									<g v="inan"/>
									<g v="masc"/>
									<g v="plur"/>
									<g v="gent"/>
								</l>
							</v>
						</tfr>
					</token>
					<token id="1375062" text="на">
						<tfr rev_id="3392606" t="на">
							<v>
								<l id="166264" t="на">
									<g v="PREP"/>
								</l>
							</v>
						</tfr>
					</token>
					<token id="1375063" text="территории">
						<tfr rev_id="4374385" t="территории">
							<v>
								<l id="345621" t="территория">
									<g v="NOUN"/>
									<g v="inan"/>
									<g v="femn"/>
									<g v="sing"/>
									<g v="loct"/>
								</l>
							</v>
						</tfr>
					</token>
					<token id="1375064" text="столицы">
						<tfr rev_id="3743835" t="столицы">
							<v>
								<l id="336588" t="столица">
									<g v="NOUN"/>
									<g v="inan"/>
									<g v="femn"/>
									<g v="sing"/>
									<g v="gent"/>
								</l>
							</v>
						</tfr>
					</token>
					<token id="1375065" text="в">
						<tfr rev_id="3025753" t="в">
							<v>
								<l id="37409" t="в">
									<g v="PREP"/>
								</l>
							</v>
						</tfr>
					</token>
					<token id="1375066" text="настоящий">
						<tfr rev_id="3025754" t="настоящий">
							<v>
								<l id="176151" t="настоящий">
									<g v="ADJF"/>
									<g v="masc"/>
									<g v="sing"/>
									<g v="nomn"/>
								</l>
							</v>
							<v>
								<l id="176151" t="настоящий">
									<g v="ADJF"/>
									<g v="inan"/>
									<g v="masc"/>
									<g v="sing"/>
									<g v="accs"/>
								</l>
							</v>
						</tfr>
					</token>
					<token id="1375067" text="момент">
						<tfr rev_id="3025755" t="момент">
							<v>
								<l id="163050" t="момент">
									<g v="NOUN"/>
									<g v="inan"/>
									<g v="masc"/>
									<g v="sing"/>
									<g v="nomn"/>
								</l>
							</v>
							<v>
								<l id="163050" t="момент">
									<g v="NOUN"/>
									<g v="inan"/>
									<g v="masc"/>
									<g v="sing"/>
									<g v="accs"/>
								</l>
							</v>
						</tfr>
					</token>
					<token id="1375068" text="составляет">
						<tfr rev_id="3025756" t="составляет">
							<v>
								<l id="330494" t="составляю">
									<g v="VERB"/>
									<g v="impf"/>
									<g v="tran"/>
									<g v="sing"/>
									<g v="3per"/>
									<g v="pres"/>
									<g v="indc"/>
								</l>
							</v>
						</tfr>
					</token>
					<token id="1375069" text="40">
						<tfr rev_id="3025757" t="40">
							<v>
								<l id="0" t="40">
									<g v="NUMB"/>
								</l>
							</v>
						</tfr>
					</token>
					<token id="1375070" text="тыс">
						<tfr rev_id="3808148" t="тыс">
							<v>
								<l id="389041" t="тыс">
									<g v="NOUN"/>
									<g v="inan"/>
									<g v="femn"/>
									<g v="Fixd"/>
									<g v="Abbr"/>
									<g v="plur"/>
									<g v="gent"/>
								</l>
							</v>
						</tfr>
					</token>
					<token id="1375071" text=".">
						<tfr rev_id="3025759" t=".">
							<v>
								<l id="0" t=".">
									<g v="PNCT"/>
								</l>
							</v>
						</tfr>
					</token>
					<token id="1375072" text="рублей">
						<tfr rev_id="3025760" t="рублей">
							<v>
								<l id="309744" t="рубль">
									<g v="NOUN"/>
									<g v="inan"/>
									<g v="masc"/>
									<g v="plur"/>
									<g v="gent"/>
								</l>
							</v>
						</tfr>
					</token>
					<token id="1375073" text="за">
						<tfr rev_id="3025761" t="за">
							<v>
								<l id="98043" t="за">
									<g v="PREP"/>
								</l>
							</v>
						</tfr>
					</token>
					<token id="1375074" text="квадратный">
						<tfr rev_id="3025762" t="квадратный">
							<v>
								<l id="131789" t="квадратный">
									<g v="ADJF"/>
									<g v="Qual"/>
									<g v="masc"/>
									<g v="sing"/>
									<g v="nomn"/>
								</l>
							</v>
							<v>
								<l id="131789" t="квадратный">
									<g v="ADJF"/>
									<g v="Qual"/>
									<g v="inan"/>
									<g v="masc"/>
									<g v="sing"/>
									<g v="accs"/>
								</l>
							</v>
						</tfr>
					</token>
					<token id="1375075" text="метр">
						<tfr rev_id="3025763" t="метр">
							<v>
								<l id="159295" t="метр">
									<g v="NOUN"/>
									<g v="anim"/>
									<g v="masc"/>
									<g v="sing"/>
									<g v="nomn"/>
								</l>
							</v>
							<v>
								<l id="159296" t="метр">
									<g v="NOUN"/>
									<g v="inan"/>
									<g v="masc"/>
									<g v="sing"/>
									<g v="nomn"/>
								</l>
							</v>
							<v>
								<l id="159296" t="метр">
									<g v="NOUN"/>
									<g v="inan"/>
									<g v="masc"/>
									<g v="sing"/>
									<g v="accs"/>
								</l>
							</v>
						</tfr>
					</token>
					<token id="1375076" text=".">
						<tfr rev_id="3025764" t=".">
							<v>
								<l id="0" t=".">
									<g v="PNCT"/>
								</l>
							</v>
						</tfr>
					</token>
				</tokens>
			</sentence>
			<sentence id="76503">
				<source>По крайне мере, эту цифру озвучил глава департамента Мосгорзаказа Леонид Моносов.</source>
				<tokens>
					<token id="1375077" text="По">
						<tfr rev_id="3025765" t="По">
							<v>
								<l id="241240" t="по">
									<g v="PREP"/>
								</l>
							</v>
						</tfr>
					</token>
					<token id="1375078" text="крайне">
						<tfr rev_id="3025766" t="крайне">
							<v>
								<l id="141513" t="крайне">
									<g v="ADVB"/>
								</l>
							</v>
							<v>
								<l id="141515" t="крайня">
									<g v="ADJS"/>
									<g v="neut"/>
									<g v="sing"/>
								</l>
							</v>
						</tfr>
					</token>
					<token id="1375079" text="мере">
						<tfr rev_id="3661633" t="мере">
							<v>
								<l id="158460" t="мера">
									<g v="NOUN"/>
									<g v="inan"/>
									<g v="femn"/>
									<g v="sing"/>
									<g v="datv"/>
								</l>
							</v>
							<v>
								<l id="158742" t="меря">
									<g v="NOUN"/>
									<g v="inan"/>
									<g v="femn"/>
									<g v="sing"/>
									<g v="datv"/>
								</l>
							</v>
						</tfr>
					</token>
					<token id="1375080" text=",">
						<tfr rev_id="3025768" t=",">
							<v>
								<l id="0" t=",">
									<g v="PNCT"/>
								</l>
							</v>
						</tfr>
					</token>
					<token id="1375081" text="эту">
						<tfr rev_id="4439067" t="эту">
							<v>
								<l id="386581" t="этот">
									<g v="ADJF"/>
									<g v="Subx"/>
									<g v="Apro"/>
									<g v="Anph"/>
									<g v="femn"/>
									<g v="sing"/>
									<g v="accs"/>
								</l>
							</v>
						</tfr>
					</token>
					<token id="1375082" text="цифру">
						<tfr rev_id="3025770" t="цифру">
							<v>
								<l id="374165" t="цифра">
									<g v="NOUN"/>
									<g v="inan"/>
									<g v="femn"/>
									<g v="sing"/>
									<g v="accs"/>
								</l>
							</v>
						</tfr>
					</token>
					<token id="1375083" text="озвучил">
						<tfr rev_id="3025771" t="озвучил">
							<v>
								<l id="204107" t="озвучил">
									<g v="VERB"/>
									<g v="perf"/>
									<g v="tran"/>
									<g v="masc"/>
									<g v="sing"/>
									<g v="past"/>
									<g v="indc"/>
								</l>
							</v>
						</tfr>
					</token>
					<token id="1375084" text="глава">
						<tfr rev_id="3760099" t="глава">
							<v>
								<l id="70790" t="глава">
									<g v="NOUN"/>
									<g v="anim"/>
									<g v="femn"/>
									<g v="Ms-f"/>
									<g v="sing"/>
									<g v="nomn"/>
								</l>
							</v>
							<v>
								<l id="70791" t="глава">
									<g v="NOUN"/>
									<g v="inan"/>
									<g v="femn"/>
									<g v="sing"/>
									<g v="nomn"/>
								</l>
							</v>
						</tfr>
					</token>
					<token id="1375085" text="департамента">
						<tfr rev_id="3025773" t="департамента">
							<v>
								<l id="81458" t="департамент">
									<g v="NOUN"/>
									<g v="inan"/>
									<g v="masc"/>
									<g v="sing"/>
									<g v="gent"/>
								</l>
							</v>
						</tfr>
					</token>
					<token id="1375086" text="Мосгорзаказа">
						<tfr rev_id="3025774" t="Мосгорзаказа">
							<v>
								<l id="0" t="мосгорзаказа">
									<g v="UNKN"/>
								</l>
							</v>
						</tfr>
					</token>
					<token id="1375087" text="Леонид">
						<tfr rev_id="3785998" t="Леонид">
							<v>
								<l id="148220" t="леонид">
									<g v="NOUN"/>
									<g v="anim"/>
									<g v="masc"/>
									<g v="Name"/>
									<g v="sing"/>
									<g v="nomn"/>
								</l>
							</v>
						</tfr>
					</token>
					<token id="1375088" text="Моносов">
						<tfr rev_id="3025776" t="Моносов">
							<v>
								<l id="0" t="моносов">
									<g v="UNKN"/>
								</l>
							</v>
						</tfr>
					</token>
					<token id="1375089" text=".">
						<tfr rev_id="3025777" t=".">
							<v>
								<l id="0" t=".">
									<g v="PNCT"/>
								</l>
							</v>
						</tfr>
					</token>
				</tokens>
			</sentence>
			<sentence id="76504">
				<source>Он также сообщил, что в текущем году его ведомство потратило на жилое строительство 61 млрд рублей из 157 выделенных бюджетом, сообщает РБК.</source>
				<tokens>
					<token id="1375090" text="Он">
						<tfr rev_id="3577548" t="Он">
							<v>
								<l id="206541" t="он">
									<g v="NPRO"/>
									<g v="masc"/>
									<g v="3per"/>
									<g v="Anph"/>
									<g v="sing"/>
									<g v="nomn"/>
								</l>
							</v>
						</tfr>
					</token>
					<token id="1375091" text="также">
						<tfr rev_id="4268951" t="также">
							<v>
								<l id="342482" t="также">
									<g v="PRCL"/>
								</l>
							</v>
						</tfr>
					</token>
					<token id="1375092" text="сообщил">
						<tfr rev_id="3025780" t="сообщил">
							<v>
								<l id="329556" t="сообщил">
									<g v="VERB"/>
									<g v="perf"/>
									<g v="tran"/>
									<g v="masc"/>
									<g v="sing"/>
									<g v="past"/>
									<g v="indc"/>
								</l>
							</v>
						</tfr>
					</token>
					<token id="1375093" text=",">
						<tfr rev_id="3025781" t=",">
							<v>
								<l id="0" t=",">
									<g v="PNCT"/>
								</l>
							</v>
						</tfr>
					</token>
					<token id="1375094" text="что">
						<tfr rev_id="3025782" t="что">
							<v>
								<l id="377004" t="что">
									<g v="CONJ"/>
								</l>
							</v>
							<v>
								<l id="377005" t="что">
									<g v="NPRO"/>
									<g v="neut"/>
									<g v="sing"/>
									<g v="nomn"/>
								</l>
							</v>
							<v>
								<l id="377005" t="что">
									<g v="NPRO"/>
									<g v="neut"/>
									<g v="sing"/>
									<g v="accs"/>
								</l>
							</v>
							<v>
								<l id="377006" t="что">
									<g v="ADVB"/>
									<g v="Ques"/>
								</l>
							</v>
							<v>
								<l id="388695" t="что">
									<g v="PRCL"/>
								</l>
							</v>
						</tfr>
					</token>
					<token id="1375095" text="в">
						<tfr rev_id="3025783" t="в">
							<v>
								<l id="37409" t="в">
									<g v="PREP"/>
								</l>
							</v>
						</tfr>
					</token>
					<token id="1375096" text="текущем">
						<tfr rev_id="3025784" t="текущем">
							<v>
								<l id="344075" t="текущий">
									<g v="ADJF"/>
									<g v="masc"/>
									<g v="sing"/>
									<g v="loct"/>
								</l>
							</v>
							<v>
								<l id="344075" t="текущий">
									<g v="ADJF"/>
									<g v="neut"/>
									<g v="sing"/>
									<g v="loct"/>
								</l>
							</v>
							<v>
								<l id="346014" t="текущий">
									<g v="PRTF"/>
									<g v="impf"/>
									<g v="intr"/>
									<g v="pres"/>
									<g v="actv"/>
									<g v="masc"/>
									<g v="sing"/>
									<g v="loct"/>
								</l>
							</v>
							<v>
								<l id="346014" t="текущий">
									<g v="PRTF"/>
									<g v="impf"/>
									<g v="intr"/>
									<g v="pres"/>
									<g v="actv"/>
									<g v="neut"/>
									<g v="sing"/>
									<g v="loct"/>
								</l>
							</v>
						</tfr>
					</token>
					<token id="1375097" text="году">
						<tfr rev_id="3538660" t="году">
							<v>
								<l id="72149" t="год">
									<g v="NOUN"/>
									<g v="inan"/>
									<g v="masc"/>
									<g v="sing"/>
									<g v="loc2"/>
								</l>
							</v>
						</tfr>
					</token>
					<token id="1375098" text="его">
						<tfr rev_id="4499640" t="его">
							<v>
								<l id="94208" t="его">
									<g v="ADJF"/>
									<g v="Fixd"/>
									<g v="Apro"/>
									<g v="Anph"/>
									<g v="masc"/>
									<g v="sing"/>
									<g v="nomn"/>
								</l>
							</v>
							<v>
								<l id="94208" t="его">
									<g v="ADJF"/>
									<g v="Fixd"/>
									<g v="Apro"/>
									<g v="Anph"/>
									<g v="masc"/>
									<g v="sing"/>
									<g v="gent"/>
								</l>
							</v>
							<v>
								<l id="94208" t="его">
									<g v="ADJF"/>
									<g v="Fixd"/>
									<g v="Apro"/>
									<g v="Anph"/>
									<g v="masc"/>
									<g v="sing"/>
									<g v="datv"/>
								</l>
							</v>
							<v>
								<l id="94208" t="его">
									<g v="ADJF"/>
									<g v="Fixd"/>
									<g v="Apro"/>
									<g v="Anph"/>
									<g v="masc"/>
									<g v="sing"/>
									<g v="accs"/>
								</l>
							</v>
							<v>
								<l id="94208" t="его">
									<g v="ADJF"/>
									<g v="Fixd"/>
									<g v="Apro"/>
									<g v="Anph"/>
									<g v="masc"/>
									<g v="sing"/>
									<g v="ablt"/>
								</l>
							</v>
							<v>
								<l id="94208" t="его">
									<g v="ADJF"/>
									<g v="Fixd"/>
									<g v="Apro"/>
									<g v="Anph"/>
									<g v="masc"/>
									<g v="sing"/>
									<g v="loct"/>
								</l>
							</v>
							<v>
								<l id="94208" t="его">
									<g v="ADJF"/>
									<g v="Fixd"/>
									<g v="Apro"/>
									<g v="Anph"/>
									<g v="femn"/>
									<g v="sing"/>
									<g v="nomn"/>
								</l>
							</v>
							<v>
								<l id="94208" t="его">
									<g v="ADJF"/>
									<g v="Fixd"/>
									<g v="Apro"/>
									<g v="Anph"/>
									<g v="femn"/>
									<g v="sing"/>
									<g v="gent"/>
								</l>
							</v>
							<v>
								<l id="94208" t="его">
									<g v="ADJF"/>
									<g v="Fixd"/>
									<g v="Apro"/>
									<g v="Anph"/>
									<g v="femn"/>
									<g v="sing"/>
									<g v="datv"/>
								</l>
							</v>
							<v>
								<l id="94208" t="его">
									<g v="ADJF"/>
									<g v="Fixd"/>
									<g v="Apro"/>
									<g v="Anph"/>
									<g v="femn"/>
									<g v="sing"/>
									<g v="accs"/>
								</l>
							</v>
							<v>
								<l id="94208" t="его">
									<g v="ADJF"/>
									<g v="Fixd"/>
									<g v="Apro"/>
									<g v="Anph"/>
									<g v="femn"/>
									<g v="sing"/>
									<g v="ablt"/>
								</l>
							</v>
							<v>
								<l id="94208" t="его">
									<g v="ADJF"/>
									<g v="Fixd"/>
									<g v="Apro"/>
									<g v="Anph"/>
									<g v="femn"/>
									<g v="sing"/>
									<g v="loct"/>
								</l>
							</v>
							<v>
								<l id="94208" t="его">
									<g v="ADJF"/>
									<g v="Fixd"/>
									<g v="Apro"/>
									<g v="Anph"/>
									<g v="neut"/>
									<g v="sing"/>
									<g v="nomn"/>
								</l>
							</v>
							<v>
								<l id="94208" t="его">
									<g v="ADJF"/>
									<g v="Fixd"/>
									<g v="Apro"/>
									<g v="Anph"/>
									<g v="neut"/>
									<g v="sing"/>
									<g v="gent"/>
								</l>
							</v>
							<v>
								<l id="94208" t="его">
									<g v="ADJF"/>
									<g v="Fixd"/>
									<g v="Apro"/>
									<g v="Anph"/>
									<g v="neut"/>
									<g v="sing"/>
									<g v="datv"/>
								</l>
							</v>
							<v>
								<l id="94208" t="его">
									<g v="ADJF"/>
									<g v="Fixd"/>
									<g v="Apro"/>
									<g v="Anph"/>
									<g v="neut"/>
									<g v="sing"/>
									<g v="accs"/>
								</l>
							</v>
							<v>
								<l id="94208" t="его">
									<g v="ADJF"/>
									<g v="Fixd"/>
									<g v="Apro"/>
									<g v="Anph"/>
									<g v="neut"/>
									<g v="sing"/>
									<g v="ablt"/>
								</l>
							</v>
							<v>
								<l id="94208" t="его">
									<g v="ADJF"/>
									<g v="Fixd"/>
									<g v="Apro"/>
									<g v="Anph"/>
									<g v="neut"/>
									<g v="sing"/>
									<g v="loct"/>
								</l>
							</v>
						</tfr>
					</token>
					<token id="1375099" text="ведомство">
						<tfr rev_id="3025787" t="ведомство">
							<v>
								<l id="40354" t="ведомство">
									<g v="NOUN"/>
									<g v="inan"/>
									<g v="neut"/>
									<g v="sing"/>
									<g v="nomn"/>
								</l>
							</v>
							<v>
								<l id="40354" t="ведомство">
									<g v="NOUN"/>
									<g v="inan"/>
									<g v="neut"/>
									<g v="sing"/>
									<g v="accs"/>
								</l>
							</v>
						</tfr>
					</token>
					<token id="1375100" text="потратило">
						<tfr rev_id="3025788" t="потратило">
							<v>
								<l id="263502" t="потратил">
									<g v="VERB"/>
									<g v="perf"/>
									<g v="tran"/>
									<g v="neut"/>
									<g v="sing"/>
									<g v="past"/>
									<g v="indc"/>
								</l>
							</v>
						</tfr>
					</token>
					<token id="1375101" text="на">
						<tfr rev_id="3393613" t="на">
							<v>
								<l id="166264" t="на">
									<g v="PREP"/>
								</l>
							</v>
						</tfr>
					</token>
					<token id="1375102" text="жилое">
						<tfr rev_id="3025790" t="жилое">
							<v>
								<l id="97384" t="жилой">
									<g v="ADJF"/>
									<g v="neut"/>
									<g v="sing"/>
									<g v="nomn"/>
								</l>
							</v>
							<v>
								<l id="97384" t="жилой">
									<g v="ADJF"/>
									<g v="neut"/>
									<g v="sing"/>
									<g v="accs"/>
								</l>
							</v>
						</tfr>
					</token>
					<token id="1375103" text="строительство">
						<tfr rev_id="3025791" t="строительство">
							<v>
								<l id="337671" t="строительство">
									<g v="NOUN"/>
									<g v="inan"/>
									<g v="neut"/>
									<g v="sing"/>
									<g v="nomn"/>
								</l>
							</v>
							<v>
								<l id="337671" t="строительство">
									<g v="NOUN"/>
									<g v="inan"/>
									<g v="neut"/>
									<g v="sing"/>
									<g v="accs"/>
								</l>
							</v>
						</tfr>
					</token>
					<token id="1375104" text="61">
						<tfr rev_id="3025792" t="61">
							<v>
								<l id="0" t="61">
									<g v="NUMB"/>
								</l>
							</v>
						</tfr>
					</token>
					<token id="1375105" text="млрд">
						<tfr rev_id="4230421" t="млрд">
							<v>
								<l id="389048" t="млрд">
									<g v="NOUN"/>
									<g v="inan"/>
									<g v="masc"/>
									<g v="Fixd"/>
									<g v="Abbr"/>
									<g v="sing"/>
									<g v="nomn"/>
								</l>
							</v>
							<v>
								<l id="389048" t="млрд">
									<g v="NOUN"/>
									<g v="inan"/>
									<g v="masc"/>
									<g v="Fixd"/>
									<g v="Abbr"/>
									<g v="sing"/>
									<g v="gent"/>
								</l>
							</v>
							<v>
								<l id="389048" t="млрд">
									<g v="NOUN"/>
									<g v="inan"/>
									<g v="masc"/>
									<g v="Fixd"/>
									<g v="Abbr"/>
									<g v="sing"/>
									<g v="datv"/>
								</l>
							</v>
							<v>
								<l id="389048" t="млрд">
									<g v="NOUN"/>
									<g v="inan"/>
									<g v="masc"/>
									<g v="Fixd"/>
									<g v="Abbr"/>
									<g v="sing"/>
									<g v="accs"/>
								</l>
							</v>
							<v>
								<l id="389048" t="млрд">
									<g v="NOUN"/>
									<g v="inan"/>
									<g v="masc"/>
									<g v="Fixd"/>
									<g v="Abbr"/>
									<g v="sing"/>
									<g v="ablt"/>
								</l>
							</v>
							<v>
								<l id="389048" t="млрд">
									<g v="NOUN"/>
									<g v="inan"/>
									<g v="masc"/>
									<g v="Fixd"/>
									<g v="Abbr"/>
									<g v="sing"/>
									<g v="loct"/>
								</l>
							</v>
						</tfr>
					</token>
					<token id="1375106" text="рублей">
						<tfr rev_id="3025794" t="рублей">
							<v>
								<l id="309744" t="рубль">
									<g v="NOUN"/>
									<g v="inan"/>
									<g v="masc"/>
									<g v="plur"/>
									<g v="gent"/>
								</l>
							</v>
						</tfr>
					</token>
					<token id="1375107" text="из">
						<tfr rev_id="3329175" t="из">
							<v>
								<l id="117677" t="из">
									<g v="PREP"/>
								</l>
							</v>
						</tfr>
					</token>
					<token id="1375108" text="157">
						<tfr rev_id="3025796" t="157">
							<v>
								<l id="0" t="157">
									<g v="NUMB"/>
								</l>
							</v>
						</tfr>
					</token>
					<token id="1375109" text="выделенных">
						<tfr rev_id="3660377" t="выделенных">
							<v>
								<l id="57034" t="выделенный">
									<g v="PRTF"/>
									<g v="perf"/>
									<g v="tran"/>
									<g v="past"/>
									<g v="pssv"/>
									<g v="plur"/>
									<g v="gent"/>
								</l>
							</v>
						</tfr>
					</token>
					<token id="1375110" text="бюджетом">
						<tfr rev_id="3025798" t="бюджетом">
							<v>
								<l id="37326" t="бюджет">
									<g v="NOUN"/>
									<g v="inan"/>
									<g v="masc"/>
									<g v="sing"/>
									<g v="ablt"/>
								</l>
							</v>
						</tfr>
					</token>
					<token id="1375111" text=",">
						<tfr rev_id="3025799" t=",">
							<v>
								<l id="0" t=",">
									<g v="PNCT"/>
								</l>
							</v>
						</tfr>
					</token>
					<token id="1375112" text="сообщает">
						<tfr rev_id="3025800" t="сообщает">
							<v>
								<l id="329538" t="сообщаю">
									<g v="VERB"/>
									<g v="impf"/>
									<g v="tran"/>
									<g v="sing"/>
									<g v="3per"/>
									<g v="pres"/>
									<g v="indc"/>
								</l>
							</v>
						</tfr>
					</token>
					<token id="1375113" text="РБК">
						<tfr rev_id="3807990" t="РБК">
							<v>
								<l id="389058" t="рбк">
									<g v="NOUN"/>
									<g v="inan"/>
									<g v="femn"/>
									<g v="Sgtm"/>
									<g v="Fixd"/>
									<g v="Abbr"/>
									<g v="Orgn"/>
									<g v="sing"/>
									<g v="nomn"/>
								</l>
							</v>
							<v>
								<l id="389058" t="рбк">
									<g v="NOUN"/>
									<g v="inan"/>
									<g v="femn"/>
									<g v="Sgtm"/>
									<g v="Fixd"/>
									<g v="Abbr"/>
									<g v="Orgn"/>
									<g v="sing"/>
									<g v="gent"/>
								</l>
							</v>
							<v>
								<l id="389058" t="рбк">
									<g v="NOUN"/>
									<g v="inan"/>
									<g v="femn"/>
									<g v="Sgtm"/>
									<g v="Fixd"/>
									<g v="Abbr"/>
									<g v="Orgn"/>
									<g v="sing"/>
									<g v="datv"/>
								</l>
							</v>
							<v>
								<l id="389058" t="рбк">
									<g v="NOUN"/>
									<g v="inan"/>
									<g v="femn"/>
									<g v="Sgtm"/>
									<g v="Fixd"/>
									<g v="Abbr"/>
									<g v="Orgn"/>
									<g v="sing"/>
									<g v="accs"/>
								</l>
							</v>
							<v>
								<l id="389058" t="рбк">
									<g v="NOUN"/>
									<g v="inan"/>
									<g v="femn"/>
									<g v="Sgtm"/>
									<g v="Fixd"/>
									<g v="Abbr"/>
									<g v="Orgn"/>
									<g v="sing"/>
									<g v="ablt"/>
								</l>
							</v>
							<v>
								<l id="389058" t="рбк">
									<g v="NOUN"/>
									<g v="inan"/>
									<g v="femn"/>
									<g v="Sgtm"/>
									<g v="Fixd"/>
									<g v="Abbr"/>
									<g v="Orgn"/>
									<g v="sing"/>
									<g v="loct"/>
								</l>
							</v>
						</tfr>
					</token>
					<token id="1375114" text=".">
						<tfr rev_id="3025802" t=".">
							<v>
								<l id="0" t=".">
									<g v="PNCT"/>
								</l>
							</v>
						</tfr>
					</token>
				</tokens>
			</sentence>
		</paragraph>
		<paragraph id="26243">
			<sentence id="76505">
				<source>Согласно статистики, которую озвучил столичный чиновник, с начала текущего года в Москве построено 600 тыс. квадратных метров социального жилья.</source>
				<tokens>
					<token id="1375115" text="Согласно">
						<tfr rev_id="4490538" t="Согласно">
							<v>
								<l id="328255" t="согласно">
									<g v="PREP"/>
								</l>
							</v>
						</tfr>
					</token>
					<token id="1375116" text="статистики">
						<tfr rev_id="4106465" t="статистики">
							<v>
								<l id="335112" t="статистика">
									<g v="NOUN"/>
									<g v="inan"/>
									<g v="femn"/>
									<g v="sing"/>
									<g v="gent"/>
								</l>
							</v>
						</tfr>
					</token>
					<token id="1375117" text=",">
						<tfr rev_id="3025805" t=",">
							<v>
								<l id="0" t=",">
									<g v="PNCT"/>
								</l>
							</v>
						</tfr>
					</token>
					<token id="1375118" text="которую">
						<tfr rev_id="3641176" t="которую">
							<v>
								<l id="141203" t="который">
									<g v="ADJF"/>
									<g v="Apro"/>
									<g v="Subx"/>
									<g v="Anph"/>
									<g v="femn"/>
									<g v="sing"/>
									<g v="accs"/>
								</l>
							</v>
						</tfr>
					</token>
					<token id="1375119" text="озвучил">
						<tfr rev_id="3025807" t="озвучил">
							<v>
								<l id="204107" t="озвучил">
									<g v="VERB"/>
									<g v="perf"/>
									<g v="tran"/>
									<g v="masc"/>
									<g v="sing"/>
									<g v="past"/>
									<g v="indc"/>
								</l>
							</v>
						</tfr>
					</token>
					<token id="1375120" text="столичный">
						<tfr rev_id="3025808" t="столичный">
							<v>
								<l id="336589" t="столичный">
									<g v="ADJF"/>
									<g v="Qual"/>
									<g v="masc"/>
									<g v="sing"/>
									<g v="nomn"/>
								</l>
							</v>
							<v>
								<l id="336589" t="столичный">
									<g v="ADJF"/>
									<g v="Qual"/>
									<g v="inan"/>
									<g v="masc"/>
									<g v="sing"/>
									<g v="accs"/>
								</l>
							</v>
						</tfr>
					</token>
					<token id="1375121" text="чиновник">
						<tfr rev_id="3025809" t="чиновник">
							<v>
								<l id="376482" t="чиновник">
									<g v="NOUN"/>
									<g v="anim"/>
									<g v="masc"/>
									<g v="sing"/>
									<g v="nomn"/>
								</l>
							</v>
						</tfr>
					</token>
					<token id="1375122" text=",">
						<tfr rev_id="3025810" t=",">
							<v>
								<l id="0" t=",">
									<g v="PNCT"/>
								</l>
							</v>
						</tfr>
					</token>
					<token id="1375123" text="с">
						<tfr rev_id="3025811" t="с">
							<v>
								<l id="311151" t="с">
									<g v="PREP"/>
								</l>
							</v>
						</tfr>
					</token>
					<token id="1375124" text="начала">
						<tfr rev_id="4203915" t="начала">
							<v>
								<l id="178196" t="начало">
									<g v="NOUN"/>
									<g v="inan"/>
									<g v="neut"/>
									<g v="sing"/>
									<g v="gent"/>
								</l>
							</v>
						</tfr>
					</token>
					<token id="1375125" text="текущего">
						<tfr rev_id="3025813" t="текущего">
							<v>
								<l id="344075" t="текущий">
									<g v="ADJF"/>
									<g v="masc"/>
									<g v="sing"/>
									<g v="gent"/>
								</l>
							</v>
							<v>
								<l id="344075" t="текущий">
									<g v="ADJF"/>
									<g v="anim"/>
									<g v="masc"/>
									<g v="sing"/>
									<g v="accs"/>
								</l>
							</v>
							<v>
								<l id="344075" t="текущий">
									<g v="ADJF"/>
									<g v="neut"/>
									<g v="sing"/>
									<g v="gent"/>
								</l>
							</v>
							<v>
								<l id="346014" t="текущий">
									<g v="PRTF"/>
									<g v="impf"/>
									<g v="intr"/>
									<g v="pres"/>
									<g v="actv"/>
									<g v="masc"/>
									<g v="sing"/>
									<g v="gent"/>
								</l>
							</v>
							<v>
								<l id="346014" t="текущий">
									<g v="PRTF"/>
									<g v="impf"/>
									<g v="intr"/>
									<g v="pres"/>
									<g v="actv"/>
									<g v="anim"/>
									<g v="masc"/>
									<g v="sing"/>
									<g v="accs"/>
								</l>
							</v>
							<v>
								<l id="346014" t="текущий">
									<g v="PRTF"/>
									<g v="impf"/>
									<g v="intr"/>
									<g v="pres"/>
									<g v="actv"/>
									<g v="neut"/>
									<g v="sing"/>
									<g v="gent"/>
								</l>
							</v>
						</tfr>
					</token>
					<token id="1375126" text="года">
						<tfr rev_id="4094742" t="года">
							<v>
								<l id="72149" t="год">
									<g v="NOUN"/>
									<g v="inan"/>
									<g v="masc"/>
									<g v="sing"/>
									<g v="gen1"/>
								</l>
							</v>
						</tfr>
					</token>
					<token id="1375127" text="в">
						<tfr rev_id="3025815" t="в">
							<v>
								<l id="37409" t="в">
									<g v="PREP"/>
								</l>
							</v>
						</tfr>
					</token>
					<token id="1375128" text="Москве">
						<tfr rev_id="3661240" t="Москве">
							<v>
								<l id="163901" t="москва">
									<g v="NOUN"/>
									<g v="inan"/>
									<g v="femn"/>
									<g v="Sgtm"/>
									<g v="Geox"/>
									<g v="sing"/>
									<g v="loct"/>
								</l>
							</v>
						</tfr>
					</token>
					<token id="1375129" text="построено">
						<tfr rev_id="3025817" t="построено">
							<v>
								<l id="262525" t="построен">
									<g v="PRTS"/>
									<g v="perf"/>
									<g v="past"/>
									<g v="pssv"/>
									<g v="neut"/>
									<g v="sing"/>
								</l>
							</v>
						</tfr>
					</token>
					<token id="1375130" text="600">
						<tfr rev_id="3025818" t="600">
							<v>
								<l id="0" t="600">
									<g v="NUMB"/>
								</l>
							</v>
						</tfr>
					</token>
					<token id="1375131" text="тыс">
						<tfr rev_id="4230524" t="тыс">
							<v>
								<l id="389041" t="тыс">
									<g v="NOUN"/>
									<g v="inan"/>
									<g v="femn"/>
									<g v="Fixd"/>
									<g v="Abbr"/>
									<g v="plur"/>
									<g v="nomn"/>
								</l>
							</v>
							<v>
								<l id="389041" t="тыс">
									<g v="NOUN"/>
									<g v="inan"/>
									<g v="femn"/>
									<g v="Fixd"/>
									<g v="Abbr"/>
									<g v="plur"/>
									<g v="gent"/>
								</l>
							</v>
							<v>
								<l id="389041" t="тыс">
									<g v="NOUN"/>
									<g v="inan"/>
									<g v="femn"/>
									<g v="Fixd"/>
									<g v="Abbr"/>
									<g v="plur"/>
									<g v="datv"/>
								</l>
							</v>
							<v>
								<l id="389041" t="тыс">
									<g v="NOUN"/>
									<g v="inan"/>
									<g v="femn"/>
									<g v="Fixd"/>
									<g v="Abbr"/>
									<g v="plur"/>
									<g v="accs"/>
								</l>
							</v>
							<v>
								<l id="389041" t="тыс">
									<g v="NOUN"/>
									<g v="inan"/>
									<g v="femn"/>
									<g v="Fixd"/>
									<g v="Abbr"/>
									<g v="plur"/>
									<g v="ablt"/>
								</l>
							</v>
							<v>
								<l id="389041" t="тыс">
									<g v="NOUN"/>
									<g v="inan"/>
									<g v="femn"/>
									<g v="Fixd"/>
									<g v="Abbr"/>
									<g v="plur"/>
									<g v="loct"/>
								</l>
							</v>
						</tfr>
					</token>
					<token id="1375132" text=".">
						<tfr rev_id="3025820" t=".">
							<v>
								<l id="0" t=".">
									<g v="PNCT"/>
								</l>
							</v>
						</tfr>
					</token>
					<token id="1375133" text="квадратных">
						<tfr rev_id="4420133" t="квадратных">
							<v>
								<l id="131789" t="квадратный">
									<g v="ADJF"/>
									<g v="Qual"/>
									<g v="plur"/>
									<g v="gent"/>
								</l>
							</v>
						</tfr>
					</token>
					<token id="1375134" text="метров">
						<tfr rev_id="4329457" t="метров">
							<v>
								<l id="159296" t="метр">
									<g v="NOUN"/>
									<g v="inan"/>
									<g v="masc"/>
									<g v="plur"/>
									<g v="gent"/>
								</l>
							</v>
						</tfr>
					</token>
					<token id="1375135" text="социального">
						<tfr rev_id="4371249" t="социального">
							<v>
								<l id="331060" t="социальный">
									<g v="ADJF"/>
									<g v="Qual"/>
									<g v="neut"/>
									<g v="sing"/>
									<g v="gent"/>
								</l>
							</v>
						</tfr>
					</token>
					<token id="1375136" text="жилья">
						<tfr rev_id="3025824" t="жилья">
							<v>
								<l id="97400" t="жильё">
									<g v="NOUN"/>
									<g v="inan"/>
									<g v="neut"/>
									<g v="Sgtm"/>
									<g v="sing"/>
									<g v="gent"/>
								</l>
							</v>
						</tfr>
					</token>
					<token id="1375137" text=".">
						<tfr rev_id="3025825" t=".">
							<v>
								<l id="0" t=".">
									<g v="PNCT"/>
								</l>
							</v>
						</tfr>
					</token>
				</tokens>
			</sentence>
			<sentence id="76506">
				<source>До конца года эта цифра вырастет ещё на 400 тысяч.</source>
				<tokens>
					<token id="1375138" text="До">
						<tfr rev_id="3025826" t="До">
							<v>
								<l id="85153" t="до">
									<g v="PREP"/>
								</l>
							</v>
						</tfr>
					</token>
					<token id="1375139" text="конца">
						<tfr rev_id="3025827" t="конца">
							<v>
								<l id="137815" t="конец">
									<g v="NOUN"/>
									<g v="inan"/>
									<g v="masc"/>
									<g v="sing"/>
									<g v="gent"/>
								</l>
							</v>
						</tfr>
					</token>
					<token id="1375140" text="года">
						<tfr rev_id="3710307" t="года">
							<v>
								<l id="72149" t="год">
									<g v="NOUN"/>
									<g v="inan"/>
									<g v="masc"/>
									<g v="sing"/>
									<g v="gen1"/>
								</l>
							</v>
						</tfr>
					</token>
					<token id="1375141" text="эта">
						<tfr rev_id="4437433" t="эта">
							<v>
								<l id="386581" t="этот">
									<g v="ADJF"/>
									<g v="Subx"/>
									<g v="Apro"/>
									<g v="Anph"/>
									<g v="femn"/>
									<g v="sing"/>
									<g v="nomn"/>
								</l>
							</v>
						</tfr>
					</token>
					<token id="1375142" text="цифра">
						<tfr rev_id="3025830" t="цифра">
							<v>
								<l id="374165" t="цифра">
									<g v="NOUN"/>
									<g v="inan"/>
									<g v="femn"/>
									<g v="sing"/>
									<g v="nomn"/>
								</l>
							</v>
						</tfr>
					</token>
					<token id="1375143" text="вырастет">
						<tfr rev_id="3025831" t="вырастет">
							<v>
								<l id="61227" t="вырос">
									<g v="VERB"/>
									<g v="perf"/>
									<g v="intr"/>
									<g v="sing"/>
									<g v="3per"/>
									<g v="futr"/>
									<g v="indc"/>
								</l>
							</v>
						</tfr>
					</token>
					<token id="1375144" text="ещё">
						<tfr rev_id="3025832" t="ещё">
							<v>
								<l id="95551" t="ещё">
									<g v="PRCL"/>
								</l>
							</v>
							<v>
								<l id="95552" t="ещё">
									<g v="ADVB"/>
								</l>
							</v>
						</tfr>
					</token>
					<token id="1375145" text="на">
						<tfr rev_id="3393335" t="на">
							<v>
								<l id="166264" t="на">
									<g v="PREP"/>
								</l>
							</v>
						</tfr>
					</token>
					<token id="1375146" text="400">
						<tfr rev_id="3025834" t="400">
							<v>
								<l id="0" t="400">
									<g v="NUMB"/>
								</l>
							</v>
						</tfr>
					</token>
					<token id="1375147" text="тысяч">
						<tfr rev_id="3025835" t="тысяч">
							<v>
								<l id="352230" t="тысяча">
									<g v="NOUN"/>
									<g v="inan"/>
									<g v="femn"/>
									<g v="plur"/>
									<g v="gent"/>
								</l>
							</v>
						</tfr>
					</token>
					<token id="1375148" text=".">
						<tfr rev_id="3025836" t=".">
							<v>
								<l id="0" t=".">
									<g v="PNCT"/>
								</l>
							</v>
						</tfr>
					</token>
				</tokens>
			</sentence>
			<sentence id="76507">
				<source>Кстати, такой же объём - 1 млн квадратных метров – будет возведён и в будущем году.</source>
				<tokens>
					<token id="1375149" text="Кстати">
						<tfr rev_id="3025837" t="Кстати">
							<v>
								<l id="144209" t="кстати">
									<g v="ADVB"/>
								</l>
							</v>
							<v>
								<l id="144210" t="кстати">
									<g v="CONJ"/>
									<g v="Prnt"/>
								</l>
							</v>
						</tfr>
					</token>
					<token id="1375150" text=",">
						<tfr rev_id="3025838" t=",">
							<v>
								<l id="0" t=",">
									<g v="PNCT"/>
								</l>
							</v>
						</tfr>
					</token>
					<token id="1375151" text="такой">
						<tfr rev_id="3695104" t="такой">
							<v>
								<l id="342491" t="такой">
									<g v="ADJF"/>
									<g v="Apro"/>
									<g v="masc"/>
									<g v="sing"/>
									<g v="nomn"/>
								</l>
							</v>
							<v>
								<l id="342491" t="такой">
									<g v="ADJF"/>
									<g v="Apro"/>
									<g v="inan"/>
									<g v="masc"/>
									<g v="sing"/>
									<g v="accs"/>
								</l>
							</v>
						</tfr>
					</token>
					<token id="1375152" text="же">
						<tfr rev_id="3025840" t="же">
							<v>
								<l id="96208" t="же">
									<g v="CONJ"/>
								</l>
							</v>
							<v>
								<l id="96209" t="же">
									<g v="PRCL"/>
								</l>
							</v>
						</tfr>
					</token>
					<token id="1375153" text="объём">
						<tfr rev_id="4075991" t="объём">
							<v>
								<l id="201701" t="объём">
									<g v="NOUN"/>
									<g v="inan"/>
									<g v="masc"/>
									<g v="sing"/>
									<g v="nomn"/>
								</l>
							</v>
						</tfr>
					</token>
					<token id="1375154" text="-">
						<tfr rev_id="3025842" t="-">
							<v>
								<l id="0" t="-">
									<g v="PNCT"/>
								</l>
							</v>
						</tfr>
					</token>
					<token id="1375155" text="1">
						<tfr rev_id="3025843" t="1">
							<v>
								<l id="0" t="1">
									<g v="NUMB"/>
								</l>
							</v>
						</tfr>
					</token>
					<token id="1375156" text="млн">
						<tfr rev_id="4136597" t="млн">
							<v>
								<l id="389040" t="млн">
									<g v="NOUN"/>
									<g v="inan"/>
									<g v="masc"/>
									<g v="Fixd"/>
									<g v="Abbr"/>
									<g v="sing"/>
									<g v="nomn"/>
								</l>
							</v>
							<v>
								<l id="389040" t="млн">
									<g v="NOUN"/>
									<g v="inan"/>
									<g v="masc"/>
									<g v="Fixd"/>
									<g v="Abbr"/>
									<g v="sing"/>
									<g v="gent"/>
								</l>
							</v>
							<v>
								<l id="389040" t="млн">
									<g v="NOUN"/>
									<g v="inan"/>
									<g v="masc"/>
									<g v="Fixd"/>
									<g v="Abbr"/>
									<g v="sing"/>
									<g v="datv"/>
								</l>
							</v>
							<v>
								<l id="389040" t="млн">
									<g v="NOUN"/>
									<g v="inan"/>
									<g v="masc"/>
									<g v="Fixd"/>
									<g v="Abbr"/>
									<g v="sing"/>
									<g v="accs"/>
								</l>
							</v>
							<v>
								<l id="389040" t="млн">
									<g v="NOUN"/>
									<g v="inan"/>
									<g v="masc"/>
									<g v="Fixd"/>
									<g v="Abbr"/>
									<g v="sing"/>
									<g v="ablt"/>
								</l>
							</v>
							<v>
								<l id="389040" t="млн">
									<g v="NOUN"/>
									<g v="inan"/>
									<g v="masc"/>
									<g v="Fixd"/>
									<g v="Abbr"/>
									<g v="sing"/>
									<g v="loct"/>
								</l>
							</v>
						</tfr>
					</token>
					<token id="1375157" text="квадратных">
						<tfr rev_id="4411363" t="квадратных">
							<v>
								<l id="131789" t="квадратный">
									<g v="ADJF"/>
									<g v="Qual"/>
									<g v="plur"/>
									<g v="gent"/>
								</l>
							</v>
						</tfr>
					</token>
					<token id="1375158" text="метров">
						<tfr rev_id="4200669" t="метров">
							<v>
								<l id="159295" t="метр">
									<g v="NOUN"/>
									<g v="anim"/>
									<g v="masc"/>
									<g v="plur"/>
									<g v="gent"/>
								</l>
							</v>
							<v>
								<l id="159296" t="метр">
									<g v="NOUN"/>
									<g v="inan"/>
									<g v="masc"/>
									<g v="plur"/>
									<g v="gent"/>
								</l>
							</v>
						</tfr>
					</token>
					<token id="1375159" text="–">
						<tfr rev_id="3025847" t="–">
							<v>
								<l id="0" t="–">
									<g v="PNCT"/>
								</l>
							</v>
						</tfr>
					</token>
					<token id="1375160" text="будет">
						<tfr rev_id="3025848" t="будет">
							<v>
								<l id="37265" t="есть">
									<g v="VERB"/>
									<g v="impf"/>
									<g v="intr"/>
									<g v="sing"/>
									<g v="3per"/>
									<g v="futr"/>
									<g v="indc"/>
								</l>
							</v>
						</tfr>
					</token>
					<token id="1375161" text="возведён">
						<tfr rev_id="3025849" t="возведён">
							<v>
								<l id="48782" t="возведён">
									<g v="PRTS"/>
									<g v="perf"/>
									<g v="past"/>
									<g v="pssv"/>
									<g v="masc"/>
									<g v="sing"/>
								</l>
							</v>
						</tfr>
					</token>
					<token id="1375162" text="и">
						<tfr rev_id="3025850" t="и">
							<v>
								<l id="116949" t="и">
									<g v="CONJ"/>
								</l>
							</v>
							<v>
								<l id="116950" t="и">
									<g v="INTJ"/>
								</l>
							</v>
						</tfr>
					</token>
					<token id="1375163" text="в">
						<tfr rev_id="3025851" t="в">
							<v>
								<l id="37409" t="в">
									<g v="PREP"/>
								</l>
							</v>
						</tfr>
					</token>
					<token id="1375164" text="будущем">
						<tfr rev_id="4349857" t="будущем">
							<v>
								<l id="35164" t="будущий">
									<g v="ADJF"/>
									<g v="masc"/>
									<g v="sing"/>
									<g v="loct"/>
								</l>
							</v>
						</tfr>
					</token>
					<token id="1375165" text="году">
						<tfr rev_id="3504308" t="году">
							<v>
								<l id="72149" t="год">
									<g v="NOUN"/>
									<g v="inan"/>
									<g v="masc"/>
									<g v="sing"/>
									<g v="loc2"/>
								</l>
							</v>
						</tfr>
					</token>
					<token id="1375166" text=".">
						<tfr rev_id="3025854" t=".">
							<v>
								<l id="0" t=".">
									<g v="PNCT"/>
								</l>
							</v>
						</tfr>
					</token>
				</tokens>
			</sentence>
		</paragraph>
	</paragraphs>
</text>
