<?xml version="1.0" ?>
<text id="3278" name="Планы атаки Ирана" parent="56">
	<tags>
		<tag>url:http://ru.wikinews.org/wiki/Планы_атаки_Ирана</tag>
		<tag>url:http://ru.wikinews.org/w/index.php?title=Планы_атаки_Ирана&amp;oldid=197775</tag>
		<tag>Гео:ВикиКатегория:Иран</tag>
		<tag>Тема:ВикиКатегория:Джордж Уокер Буш</tag>
		<tag>Год:2007</tag>
		<tag>Автор:http://ru.wikinews.org/wiki/Участник:Ygrek</tag>
		<tag>Дата:20/01</tag>
		<tag>Тема:ВикиКатегория:Политика</tag>
		<tag>Гео:ВикиКатегория:Азия</tag>
		<tag>Гео:ВикиКатегория:США</tag>
	</tags>
	<paragraphs>
		<paragraph id="26789">
			<sentence id="77847">
				<source>Планы атаки Ирана</source>
				<tokens>
					<token id="1398724" text="Планы">
						<tfr rev_id="3765271" t="Планы">
							<v>
								<l id="239677" t="план">
									<g v="NOUN"/>
									<g v="inan"/>
									<g v="masc"/>
									<g v="plur"/>
									<g v="nomn"/>
								</l>
							</v>
						</tfr>
					</token>
					<token id="1398725" text="атаки">
						<tfr rev_id="4101419" t="атаки">
							<v>
								<l id="19312" t="атака">
									<g v="NOUN"/>
									<g v="inan"/>
									<g v="femn"/>
									<g v="sing"/>
									<g v="gent"/>
								</l>
							</v>
						</tfr>
					</token>
					<token id="1398726" text="Ирана">
						<tfr rev_id="3050614" t="Ирана">
							<v>
								<l id="123907" t="иран">
									<g v="NOUN"/>
									<g v="inan"/>
									<g v="masc"/>
									<g v="Geox"/>
									<g v="sing"/>
									<g v="gent"/>
								</l>
							</v>
						</tfr>
					</token>
				</tokens>
			</sentence>
		</paragraph>
		<paragraph id="26790">
			<sentence id="77848">
				<source>Бывший сотрудник одной из тайных служб США сообщает, что США планируют ограниченную военную акцию против Иранских атомных центров.</source>
				<tokens>
					<token id="1398727" text="Бывший">
						<tfr rev_id="3050615" t="Бывший">
							<v>
								<l id="37002" t="бывший">
									<g v="ADJF"/>
									<g v="masc"/>
									<g v="sing"/>
									<g v="nomn"/>
								</l>
							</v>
							<v>
								<l id="37002" t="бывший">
									<g v="ADJF"/>
									<g v="inan"/>
									<g v="masc"/>
									<g v="sing"/>
									<g v="accs"/>
								</l>
							</v>
							<v>
								<l id="37267" t="бывший">
									<g v="PRTF"/>
									<g v="impf"/>
									<g v="intr"/>
									<g v="past"/>
									<g v="actv"/>
									<g v="masc"/>
									<g v="sing"/>
									<g v="nomn"/>
								</l>
							</v>
							<v>
								<l id="37267" t="бывший">
									<g v="PRTF"/>
									<g v="impf"/>
									<g v="intr"/>
									<g v="past"/>
									<g v="actv"/>
									<g v="inan"/>
									<g v="masc"/>
									<g v="sing"/>
									<g v="accs"/>
								</l>
							</v>
						</tfr>
					</token>
					<token id="1398728" text="сотрудник">
						<tfr rev_id="3050616" t="сотрудник">
							<v>
								<l id="330867" t="сотрудник">
									<g v="NOUN"/>
									<g v="anim"/>
									<g v="masc"/>
									<g v="sing"/>
									<g v="nomn"/>
								</l>
							</v>
						</tfr>
					</token>
					<token id="1398729" text="одной">
						<tfr rev_id="4423200" t="одной">
							<v>
								<l id="203319" t="один">
									<g v="ADJF"/>
									<g v="Apro"/>
									<g v="Anum"/>
									<g v="femn"/>
									<g v="sing"/>
									<g v="gent"/>
								</l>
							</v>
						</tfr>
					</token>
					<token id="1398730" text="из">
						<tfr rev_id="3396678" t="из">
							<v>
								<l id="117677" t="из">
									<g v="PREP"/>
								</l>
							</v>
						</tfr>
					</token>
					<token id="1398731" text="тайных">
						<tfr rev_id="4195327" t="тайных">
							<v>
								<l id="342432" t="тайный">
									<g v="ADJF"/>
									<g v="plur"/>
									<g v="gent"/>
								</l>
							</v>
						</tfr>
					</token>
					<token id="1398732" text="служб">
						<tfr rev_id="3050620" t="служб">
							<v>
								<l id="325377" t="служба">
									<g v="NOUN"/>
									<g v="inan"/>
									<g v="femn"/>
									<g v="plur"/>
									<g v="gent"/>
								</l>
							</v>
						</tfr>
					</token>
					<token id="1398733" text="США">
						<tfr rev_id="3811756" t="США">
							<v>
								<l id="341371" t="сша">
									<g v="NOUN"/>
									<g v="inan"/>
									<g v="GNdr"/>
									<g v="Pltm"/>
									<g v="Fixd"/>
									<g v="Abbr"/>
									<g v="Geox"/>
									<g v="plur"/>
									<g v="nomn"/>
								</l>
							</v>
							<v>
								<l id="341371" t="сша">
									<g v="NOUN"/>
									<g v="inan"/>
									<g v="GNdr"/>
									<g v="Pltm"/>
									<g v="Fixd"/>
									<g v="Abbr"/>
									<g v="Geox"/>
									<g v="plur"/>
									<g v="gent"/>
								</l>
							</v>
							<v>
								<l id="341371" t="сша">
									<g v="NOUN"/>
									<g v="inan"/>
									<g v="GNdr"/>
									<g v="Pltm"/>
									<g v="Fixd"/>
									<g v="Abbr"/>
									<g v="Geox"/>
									<g v="plur"/>
									<g v="datv"/>
								</l>
							</v>
							<v>
								<l id="341371" t="сша">
									<g v="NOUN"/>
									<g v="inan"/>
									<g v="GNdr"/>
									<g v="Pltm"/>
									<g v="Fixd"/>
									<g v="Abbr"/>
									<g v="Geox"/>
									<g v="plur"/>
									<g v="accs"/>
								</l>
							</v>
							<v>
								<l id="341371" t="сша">
									<g v="NOUN"/>
									<g v="inan"/>
									<g v="GNdr"/>
									<g v="Pltm"/>
									<g v="Fixd"/>
									<g v="Abbr"/>
									<g v="Geox"/>
									<g v="plur"/>
									<g v="ablt"/>
								</l>
							</v>
							<v>
								<l id="341371" t="сша">
									<g v="NOUN"/>
									<g v="inan"/>
									<g v="GNdr"/>
									<g v="Pltm"/>
									<g v="Fixd"/>
									<g v="Abbr"/>
									<g v="Geox"/>
									<g v="plur"/>
									<g v="loct"/>
								</l>
							</v>
						</tfr>
					</token>
					<token id="1398734" text="сообщает">
						<tfr rev_id="3050622" t="сообщает">
							<v>
								<l id="329538" t="сообщаю">
									<g v="VERB"/>
									<g v="impf"/>
									<g v="tran"/>
									<g v="sing"/>
									<g v="3per"/>
									<g v="pres"/>
									<g v="indc"/>
								</l>
							</v>
						</tfr>
					</token>
					<token id="1398735" text=",">
						<tfr rev_id="3050623" t=",">
							<v>
								<l id="0" t=",">
									<g v="PNCT"/>
								</l>
							</v>
						</tfr>
					</token>
					<token id="1398736" text="что">
						<tfr rev_id="3050624" t="что">
							<v>
								<l id="377004" t="что">
									<g v="CONJ"/>
								</l>
							</v>
							<v>
								<l id="377005" t="что">
									<g v="NPRO"/>
									<g v="neut"/>
									<g v="sing"/>
									<g v="nomn"/>
								</l>
							</v>
							<v>
								<l id="377005" t="что">
									<g v="NPRO"/>
									<g v="neut"/>
									<g v="sing"/>
									<g v="accs"/>
								</l>
							</v>
							<v>
								<l id="377006" t="что">
									<g v="ADVB"/>
									<g v="Ques"/>
								</l>
							</v>
							<v>
								<l id="388695" t="что">
									<g v="PRCL"/>
								</l>
							</v>
						</tfr>
					</token>
					<token id="1398737" text="США">
						<tfr rev_id="3811757" t="США">
							<v>
								<l id="341371" t="сша">
									<g v="NOUN"/>
									<g v="inan"/>
									<g v="GNdr"/>
									<g v="Pltm"/>
									<g v="Fixd"/>
									<g v="Abbr"/>
									<g v="Geox"/>
									<g v="plur"/>
									<g v="nomn"/>
								</l>
							</v>
							<v>
								<l id="341371" t="сша">
									<g v="NOUN"/>
									<g v="inan"/>
									<g v="GNdr"/>
									<g v="Pltm"/>
									<g v="Fixd"/>
									<g v="Abbr"/>
									<g v="Geox"/>
									<g v="plur"/>
									<g v="gent"/>
								</l>
							</v>
							<v>
								<l id="341371" t="сша">
									<g v="NOUN"/>
									<g v="inan"/>
									<g v="GNdr"/>
									<g v="Pltm"/>
									<g v="Fixd"/>
									<g v="Abbr"/>
									<g v="Geox"/>
									<g v="plur"/>
									<g v="datv"/>
								</l>
							</v>
							<v>
								<l id="341371" t="сша">
									<g v="NOUN"/>
									<g v="inan"/>
									<g v="GNdr"/>
									<g v="Pltm"/>
									<g v="Fixd"/>
									<g v="Abbr"/>
									<g v="Geox"/>
									<g v="plur"/>
									<g v="accs"/>
								</l>
							</v>
							<v>
								<l id="341371" t="сша">
									<g v="NOUN"/>
									<g v="inan"/>
									<g v="GNdr"/>
									<g v="Pltm"/>
									<g v="Fixd"/>
									<g v="Abbr"/>
									<g v="Geox"/>
									<g v="plur"/>
									<g v="ablt"/>
								</l>
							</v>
							<v>
								<l id="341371" t="сша">
									<g v="NOUN"/>
									<g v="inan"/>
									<g v="GNdr"/>
									<g v="Pltm"/>
									<g v="Fixd"/>
									<g v="Abbr"/>
									<g v="Geox"/>
									<g v="plur"/>
									<g v="loct"/>
								</l>
							</v>
						</tfr>
					</token>
					<token id="1398738" text="планируют">
						<tfr rev_id="3050626" t="планируют">
							<v>
								<l id="239713" t="планирую">
									<g v="VERB"/>
									<g v="impf"/>
									<g v="tran"/>
									<g v="plur"/>
									<g v="3per"/>
									<g v="pres"/>
									<g v="indc"/>
								</l>
							</v>
						</tfr>
					</token>
					<token id="1398739" text="ограниченную">
						<tfr rev_id="3050627" t="ограниченную">
							<v>
								<l id="202918" t="ограниченный">
									<g v="ADJF"/>
									<g v="Qual"/>
									<g v="femn"/>
									<g v="sing"/>
									<g v="accs"/>
								</l>
							</v>
							<v>
								<l id="202940" t="ограниченный">
									<g v="PRTF"/>
									<g v="perf"/>
									<g v="tran"/>
									<g v="past"/>
									<g v="pssv"/>
									<g v="femn"/>
									<g v="sing"/>
									<g v="accs"/>
								</l>
							</v>
						</tfr>
					</token>
					<token id="1398740" text="военную">
						<tfr rev_id="4494109" t="военную">
							<v>
								<l id="48619" t="военный">
									<g v="ADJF"/>
									<g v="femn"/>
									<g v="sing"/>
									<g v="accs"/>
								</l>
							</v>
						</tfr>
					</token>
					<token id="1398741" text="акцию">
						<tfr rev_id="3050629" t="акцию">
							<v>
								<l id="7961" t="акция">
									<g v="NOUN"/>
									<g v="inan"/>
									<g v="femn"/>
									<g v="sing"/>
									<g v="accs"/>
								</l>
							</v>
						</tfr>
					</token>
					<token id="1398742" text="против">
						<tfr rev_id="4266333" t="против">
							<v>
								<l id="285790" t="против">
									<g v="PREP"/>
								</l>
							</v>
							<v>
								<l id="285791" t="против">
									<g v="ADVB"/>
									<g v="Prdx"/>
								</l>
							</v>
						</tfr>
					</token>
					<token id="1398743" text="Иранских">
						<tfr rev_id="3050631" t="Иранских">
							<v>
								<l id="123920" t="иранский">
									<g v="ADJF"/>
									<g v="plur"/>
									<g v="gent"/>
								</l>
							</v>
							<v>
								<l id="123920" t="иранский">
									<g v="ADJF"/>
									<g v="anim"/>
									<g v="plur"/>
									<g v="accs"/>
								</l>
							</v>
							<v>
								<l id="123920" t="иранский">
									<g v="ADJF"/>
									<g v="plur"/>
									<g v="loct"/>
								</l>
							</v>
						</tfr>
					</token>
					<token id="1398744" text="атомных">
						<tfr rev_id="4401407" t="атомных">
							<v>
								<l id="19606" t="атомный">
									<g v="ADJF"/>
									<g v="Qual"/>
									<g v="plur"/>
									<g v="gent"/>
								</l>
							</v>
						</tfr>
					</token>
					<token id="1398745" text="центров">
						<tfr rev_id="3050633" t="центров">
							<v>
								<l id="373369" t="центр">
									<g v="NOUN"/>
									<g v="inan"/>
									<g v="masc"/>
									<g v="plur"/>
									<g v="gent"/>
								</l>
							</v>
						</tfr>
					</token>
					<token id="1398746" text=".">
						<tfr rev_id="3050634" t=".">
							<v>
								<l id="0" t=".">
									<g v="PNCT"/>
								</l>
							</v>
						</tfr>
					</token>
				</tokens>
			</sentence>
			<sentence id="77849">
				<source>Такие военные акции приведут к войне против Ирана, говорит эксперт по Ближнему востоку Уэйн Уайт (Wayne White), который видел часть этих планов.</source>
				<tokens>
					<token id="1398747" text="Такие">
						<tfr rev_id="3050635" t="Такие">
							<v>
								<l id="342491" t="такой">
									<g v="ADJF"/>
									<g v="Apro"/>
									<g v="plur"/>
									<g v="nomn"/>
								</l>
							</v>
							<v>
								<l id="342491" t="такой">
									<g v="ADJF"/>
									<g v="Apro"/>
									<g v="inan"/>
									<g v="plur"/>
									<g v="accs"/>
								</l>
							</v>
						</tfr>
					</token>
					<token id="1398748" text="военные">
						<tfr rev_id="4494190" t="военные">
							<v>
								<l id="48619" t="военный">
									<g v="ADJF"/>
									<g v="plur"/>
									<g v="nomn"/>
								</l>
							</v>
							<v>
								<l id="48619" t="военный">
									<g v="ADJF"/>
									<g v="inan"/>
									<g v="plur"/>
									<g v="accs"/>
								</l>
							</v>
						</tfr>
					</token>
					<token id="1398749" text="акции">
						<tfr rev_id="4237234" t="акции">
							<v>
								<l id="7961" t="акция">
									<g v="NOUN"/>
									<g v="inan"/>
									<g v="femn"/>
									<g v="plur"/>
									<g v="nomn"/>
								</l>
							</v>
						</tfr>
					</token>
					<token id="1398750" text="приведут">
						<tfr rev_id="3050638" t="приведут">
							<v>
								<l id="269205" t="привёл">
									<g v="VERB"/>
									<g v="perf"/>
									<g v="tran"/>
									<g v="plur"/>
									<g v="3per"/>
									<g v="futr"/>
									<g v="indc"/>
								</l>
							</v>
						</tfr>
					</token>
					<token id="1398751" text="к">
						<tfr rev_id="3050639" t="к">
							<v>
								<l id="127460" t="к">
									<g v="PREP"/>
								</l>
							</v>
						</tfr>
					</token>
					<token id="1398752" text="войне">
						<tfr rev_id="3660865" t="войне">
							<v>
								<l id="49721" t="война">
									<g v="NOUN"/>
									<g v="inan"/>
									<g v="femn"/>
									<g v="sing"/>
									<g v="datv"/>
								</l>
							</v>
						</tfr>
					</token>
					<token id="1398753" text="против">
						<tfr rev_id="4266334" t="против">
							<v>
								<l id="285790" t="против">
									<g v="PREP"/>
								</l>
							</v>
							<v>
								<l id="285791" t="против">
									<g v="ADVB"/>
									<g v="Prdx"/>
								</l>
							</v>
						</tfr>
					</token>
					<token id="1398754" text="Ирана">
						<tfr rev_id="3050642" t="Ирана">
							<v>
								<l id="123907" t="иран">
									<g v="NOUN"/>
									<g v="inan"/>
									<g v="masc"/>
									<g v="Geox"/>
									<g v="sing"/>
									<g v="gent"/>
								</l>
							</v>
						</tfr>
					</token>
					<token id="1398755" text=",">
						<tfr rev_id="3050643" t=",">
							<v>
								<l id="0" t=",">
									<g v="PNCT"/>
								</l>
							</v>
						</tfr>
					</token>
					<token id="1398756" text="говорит">
						<tfr rev_id="3050644" t="говорит">
							<v>
								<l id="72053" t="говорю">
									<g v="VERB"/>
									<g v="impf"/>
									<g v="tran"/>
									<g v="sing"/>
									<g v="3per"/>
									<g v="pres"/>
									<g v="indc"/>
								</l>
							</v>
						</tfr>
					</token>
					<token id="1398757" text="эксперт">
						<tfr rev_id="3050645" t="эксперт">
							<v>
								<l id="383582" t="эксперт">
									<g v="NOUN"/>
									<g v="anim"/>
									<g v="masc"/>
									<g v="sing"/>
									<g v="nomn"/>
								</l>
							</v>
						</tfr>
					</token>
					<token id="1398758" text="по">
						<tfr rev_id="3050646" t="по">
							<v>
								<l id="241240" t="по">
									<g v="PREP"/>
								</l>
							</v>
						</tfr>
					</token>
					<token id="1398759" text="Ближнему">
						<tfr rev_id="4405081" t="Ближнему">
							<v>
								<l id="30843" t="ближний">
									<g v="ADJF"/>
									<g v="masc"/>
									<g v="sing"/>
									<g v="datv"/>
								</l>
							</v>
						</tfr>
					</token>
					<token id="1398760" text="востоку">
						<tfr rev_id="3050648" t="востоку">
							<v>
								<l id="51910" t="восток">
									<g v="NOUN"/>
									<g v="inan"/>
									<g v="masc"/>
									<g v="sing"/>
									<g v="datv"/>
								</l>
							</v>
							<v>
								<l id="51911" t="восток">
									<g v="NOUN"/>
									<g v="inan"/>
									<g v="masc"/>
									<g v="Geox"/>
									<g v="sing"/>
									<g v="datv"/>
								</l>
							</v>
						</tfr>
					</token>
					<token id="1398761" text="Уэйн">
						<tfr rev_id="4453023" t="Уэйн">
							<v>
								<l id="390710" t="уэйн">
									<g v="NOUN"/>
									<g v="anim"/>
									<g v="masc"/>
									<g v="Name"/>
									<g v="sing"/>
									<g v="nomn"/>
								</l>
							</v>
						</tfr>
					</token>
					<token id="1398762" text="Уайт">
						<tfr rev_id="3050650" t="Уайт">
							<v>
								<l id="352827" t="уайт">
									<g v="NOUN"/>
									<g v="anim"/>
									<g v="masc"/>
									<g v="Name"/>
									<g v="sing"/>
									<g v="nomn"/>
								</l>
							</v>
						</tfr>
					</token>
					<token id="1398763" text="(">
						<tfr rev_id="3050651" t="(">
							<v>
								<l id="0" t="(">
									<g v="PNCT"/>
								</l>
							</v>
						</tfr>
					</token>
					<token id="1398764" text="Wayne">
						<tfr rev_id="3050652" t="Wayne">
							<v>
								<l id="0" t="Wayne">
									<g v="LATN"/>
								</l>
							</v>
						</tfr>
					</token>
					<token id="1398765" text="White">
						<tfr rev_id="3050653" t="White">
							<v>
								<l id="0" t="White">
									<g v="LATN"/>
								</l>
							</v>
						</tfr>
					</token>
					<token id="1398766" text=")">
						<tfr rev_id="3050654" t=")">
							<v>
								<l id="0" t=")">
									<g v="PNCT"/>
								</l>
							</v>
						</tfr>
					</token>
					<token id="1398767" text=",">
						<tfr rev_id="3050655" t=",">
							<v>
								<l id="0" t=",">
									<g v="PNCT"/>
								</l>
							</v>
						</tfr>
					</token>
					<token id="1398768" text="который">
						<tfr rev_id="3638035" t="который">
							<v>
								<l id="141203" t="который">
									<g v="ADJF"/>
									<g v="Apro"/>
									<g v="Subx"/>
									<g v="Anph"/>
									<g v="masc"/>
									<g v="sing"/>
									<g v="nomn"/>
								</l>
							</v>
							<v>
								<l id="141203" t="который">
									<g v="ADJF"/>
									<g v="Apro"/>
									<g v="Subx"/>
									<g v="Anph"/>
									<g v="inan"/>
									<g v="masc"/>
									<g v="sing"/>
									<g v="accs"/>
								</l>
							</v>
						</tfr>
					</token>
					<token id="1398769" text="видел">
						<tfr rev_id="3050657" t="видел">
							<v>
								<l id="44564" t="вижу">
									<g v="VERB"/>
									<g v="impf"/>
									<g v="tran"/>
									<g v="masc"/>
									<g v="sing"/>
									<g v="past"/>
									<g v="indc"/>
								</l>
							</v>
						</tfr>
					</token>
					<token id="1398770" text="часть">
						<tfr rev_id="3050658" t="часть">
							<v>
								<l id="374820" t="часть">
									<g v="NOUN"/>
									<g v="inan"/>
									<g v="femn"/>
									<g v="sing"/>
									<g v="nomn"/>
								</l>
							</v>
							<v>
								<l id="374820" t="часть">
									<g v="NOUN"/>
									<g v="inan"/>
									<g v="femn"/>
									<g v="sing"/>
									<g v="accs"/>
								</l>
							</v>
						</tfr>
					</token>
					<token id="1398771" text="этих">
						<tfr rev_id="4447378" t="этих">
							<v>
								<l id="386581" t="этот">
									<g v="ADJF"/>
									<g v="Subx"/>
									<g v="Apro"/>
									<g v="Anph"/>
									<g v="plur"/>
									<g v="gent"/>
								</l>
							</v>
						</tfr>
					</token>
					<token id="1398772" text="планов">
						<tfr rev_id="3050660" t="планов">
							<v>
								<l id="239677" t="план">
									<g v="NOUN"/>
									<g v="inan"/>
									<g v="masc"/>
									<g v="plur"/>
									<g v="gent"/>
								</l>
							</v>
						</tfr>
					</token>
					<token id="1398773" text=".">
						<tfr rev_id="3050661" t=".">
							<v>
								<l id="0" t=".">
									<g v="PNCT"/>
								</l>
							</v>
						</tfr>
					</token>
				</tokens>
			</sentence>
			<sentence id="77850">
				<source>Речь не идёт об отдельных точно нацеленных ударах.</source>
				<tokens>
					<token id="1398774" text="Речь">
						<tfr rev_id="3050662" t="Речь">
							<v>
								<l id="307325" t="речь">
									<g v="NOUN"/>
									<g v="inan"/>
									<g v="femn"/>
									<g v="sing"/>
									<g v="nomn"/>
								</l>
							</v>
							<v>
								<l id="307325" t="речь">
									<g v="NOUN"/>
									<g v="inan"/>
									<g v="femn"/>
									<g v="sing"/>
									<g v="accs"/>
								</l>
							</v>
						</tfr>
					</token>
					<token id="1398775" text="не">
						<tfr rev_id="3050663" t="не">
							<v>
								<l id="178876" t="не">
									<g v="PRCL"/>
								</l>
							</v>
						</tfr>
					</token>
					<token id="1398776" text="идёт">
						<tfr rev_id="3050664" t="идёт">
							<v>
								<l id="117566" t="иду">
									<g v="VERB"/>
									<g v="impf"/>
									<g v="intr"/>
									<g v="sing"/>
									<g v="3per"/>
									<g v="pres"/>
									<g v="indc"/>
								</l>
							</v>
						</tfr>
					</token>
					<token id="1398777" text="об">
						<tfr rev_id="3050665" t="об">
							<v>
								<l id="192977" t="о">
									<g v="PREP"/>
									<g v="Vpre"/>
								</l>
							</v>
						</tfr>
					</token>
					<token id="1398778" text="отдельных">
						<tfr rev_id="3050666" t="отдельных">
							<v>
								<l id="213415" t="отдельный">
									<g v="ADJF"/>
									<g v="Qual"/>
									<g v="plur"/>
									<g v="gent"/>
								</l>
							</v>
							<v>
								<l id="213415" t="отдельный">
									<g v="ADJF"/>
									<g v="Qual"/>
									<g v="anim"/>
									<g v="plur"/>
									<g v="accs"/>
								</l>
							</v>
							<v>
								<l id="213415" t="отдельный">
									<g v="ADJF"/>
									<g v="Qual"/>
									<g v="plur"/>
									<g v="loct"/>
								</l>
							</v>
						</tfr>
					</token>
					<token id="1398779" text="точно">
						<tfr rev_id="3050667" t="точно">
							<v>
								<l id="348514" t="точно">
									<g v="ADVB"/>
								</l>
							</v>
							<v>
								<l id="348515" t="точно">
									<g v="CONJ"/>
								</l>
							</v>
							<v>
								<l id="348516" t="точно">
									<g v="PRCL"/>
								</l>
							</v>
							<v>
								<l id="348521" t="точен">
									<g v="ADJS"/>
									<g v="Qual"/>
									<g v="neut"/>
									<g v="sing"/>
								</l>
							</v>
						</tfr>
					</token>
					<token id="1398780" text="нацеленных">
						<tfr rev_id="3050668" t="нацеленных">
							<v>
								<l id="178047" t="нацеленный">
									<g v="PRTF"/>
									<g v="perf"/>
									<g v="tran"/>
									<g v="past"/>
									<g v="pssv"/>
									<g v="plur"/>
									<g v="gent"/>
								</l>
							</v>
							<v>
								<l id="178047" t="нацеленный">
									<g v="PRTF"/>
									<g v="perf"/>
									<g v="tran"/>
									<g v="past"/>
									<g v="pssv"/>
									<g v="anim"/>
									<g v="plur"/>
									<g v="accs"/>
								</l>
							</v>
							<v>
								<l id="178047" t="нацеленный">
									<g v="PRTF"/>
									<g v="perf"/>
									<g v="tran"/>
									<g v="past"/>
									<g v="pssv"/>
									<g v="plur"/>
									<g v="loct"/>
								</l>
							</v>
						</tfr>
					</token>
					<token id="1398781" text="ударах">
						<tfr rev_id="3050669" t="ударах">
							<v>
								<l id="354672" t="удар">
									<g v="NOUN"/>
									<g v="inan"/>
									<g v="masc"/>
									<g v="plur"/>
									<g v="loct"/>
								</l>
							</v>
						</tfr>
					</token>
					<token id="1398782" text=".">
						<tfr rev_id="3050670" t=".">
							<v>
								<l id="0" t=".">
									<g v="PNCT"/>
								</l>
							</v>
						</tfr>
					</token>
				</tokens>
			</sentence>
			<sentence id="77851">
				<source>Речь идёт о войне против Ирана, которая приведёт к длительной дестабилизации ситуации на Ближнем востоке, сказал Уайт, который до мая 2005 года работал в министерстве иностранных дел США.</source>
				<tokens>
					<token id="1398783" text="Речь">
						<tfr rev_id="3050671" t="Речь">
							<v>
								<l id="307325" t="речь">
									<g v="NOUN"/>
									<g v="inan"/>
									<g v="femn"/>
									<g v="sing"/>
									<g v="nomn"/>
								</l>
							</v>
							<v>
								<l id="307325" t="речь">
									<g v="NOUN"/>
									<g v="inan"/>
									<g v="femn"/>
									<g v="sing"/>
									<g v="accs"/>
								</l>
							</v>
						</tfr>
					</token>
					<token id="1398784" text="идёт">
						<tfr rev_id="3050672" t="идёт">
							<v>
								<l id="117566" t="иду">
									<g v="VERB"/>
									<g v="impf"/>
									<g v="intr"/>
									<g v="sing"/>
									<g v="3per"/>
									<g v="pres"/>
									<g v="indc"/>
								</l>
							</v>
						</tfr>
					</token>
					<token id="1398785" text="о">
						<tfr rev_id="3392239" t="о">
							<v>
								<l id="192977" t="о">
									<g v="PREP"/>
								</l>
							</v>
						</tfr>
					</token>
					<token id="1398786" text="войне">
						<tfr rev_id="3667204" t="войне">
							<v>
								<l id="49721" t="война">
									<g v="NOUN"/>
									<g v="inan"/>
									<g v="femn"/>
									<g v="sing"/>
									<g v="loct"/>
								</l>
							</v>
						</tfr>
					</token>
					<token id="1398787" text="против">
						<tfr rev_id="4485297" t="против">
							<v>
								<l id="285790" t="против">
									<g v="PREP"/>
								</l>
							</v>
						</tfr>
					</token>
					<token id="1398788" text="Ирана">
						<tfr rev_id="3050676" t="Ирана">
							<v>
								<l id="123907" t="иран">
									<g v="NOUN"/>
									<g v="inan"/>
									<g v="masc"/>
									<g v="Geox"/>
									<g v="sing"/>
									<g v="gent"/>
								</l>
							</v>
						</tfr>
					</token>
					<token id="1398789" text=",">
						<tfr rev_id="3050677" t=",">
							<v>
								<l id="0" t=",">
									<g v="PNCT"/>
								</l>
							</v>
						</tfr>
					</token>
					<token id="1398790" text="которая">
						<tfr rev_id="3640131" t="которая">
							<v>
								<l id="141203" t="который">
									<g v="ADJF"/>
									<g v="Apro"/>
									<g v="Subx"/>
									<g v="Anph"/>
									<g v="femn"/>
									<g v="sing"/>
									<g v="nomn"/>
								</l>
							</v>
						</tfr>
					</token>
					<token id="1398791" text="приведёт">
						<tfr rev_id="3050679" t="приведёт">
							<v>
								<l id="269205" t="привёл">
									<g v="VERB"/>
									<g v="perf"/>
									<g v="tran"/>
									<g v="sing"/>
									<g v="3per"/>
									<g v="futr"/>
									<g v="indc"/>
								</l>
							</v>
						</tfr>
					</token>
					<token id="1398792" text="к">
						<tfr rev_id="3050680" t="к">
							<v>
								<l id="127460" t="к">
									<g v="PREP"/>
								</l>
							</v>
						</tfr>
					</token>
					<token id="1398793" text="длительной">
						<tfr rev_id="3050681" t="длительной">
							<v>
								<l id="85017" t="длительный">
									<g v="ADJF"/>
									<g v="Qual"/>
									<g v="femn"/>
									<g v="sing"/>
									<g v="gent"/>
								</l>
							</v>
							<v>
								<l id="85017" t="длительный">
									<g v="ADJF"/>
									<g v="Qual"/>
									<g v="femn"/>
									<g v="sing"/>
									<g v="datv"/>
								</l>
							</v>
							<v>
								<l id="85017" t="длительный">
									<g v="ADJF"/>
									<g v="Qual"/>
									<g v="femn"/>
									<g v="sing"/>
									<g v="ablt"/>
								</l>
							</v>
							<v>
								<l id="85017" t="длительный">
									<g v="ADJF"/>
									<g v="Qual"/>
									<g v="femn"/>
									<g v="sing"/>
									<g v="loct"/>
								</l>
							</v>
						</tfr>
					</token>
					<token id="1398794" text="дестабилизации">
						<tfr rev_id="4380935" t="дестабилизации">
							<v>
								<l id="82011" t="дестабилизация">
									<g v="NOUN"/>
									<g v="inan"/>
									<g v="femn"/>
									<g v="sing"/>
									<g v="datv"/>
								</l>
							</v>
						</tfr>
					</token>
					<token id="1398795" text="ситуации">
						<tfr rev_id="4380936" t="ситуации">
							<v>
								<l id="321441" t="ситуация">
									<g v="NOUN"/>
									<g v="inan"/>
									<g v="femn"/>
									<g v="sing"/>
									<g v="gent"/>
								</l>
							</v>
						</tfr>
					</token>
					<token id="1398796" text="на">
						<tfr rev_id="3392813" t="на">
							<v>
								<l id="166264" t="на">
									<g v="PREP"/>
								</l>
							</v>
						</tfr>
					</token>
					<token id="1398797" text="Ближнем">
						<tfr rev_id="4308924" t="Ближнем">
							<v>
								<l id="30843" t="ближний">
									<g v="ADJF"/>
									<g v="masc"/>
									<g v="sing"/>
									<g v="loct"/>
								</l>
							</v>
						</tfr>
					</token>
					<token id="1398798" text="востоке">
						<tfr rev_id="3050686" t="востоке">
							<v>
								<l id="51910" t="восток">
									<g v="NOUN"/>
									<g v="inan"/>
									<g v="masc"/>
									<g v="sing"/>
									<g v="loct"/>
								</l>
							</v>
							<v>
								<l id="51911" t="восток">
									<g v="NOUN"/>
									<g v="inan"/>
									<g v="masc"/>
									<g v="Geox"/>
									<g v="sing"/>
									<g v="loct"/>
								</l>
							</v>
						</tfr>
					</token>
					<token id="1398799" text=",">
						<tfr rev_id="3050687" t=",">
							<v>
								<l id="0" t=",">
									<g v="PNCT"/>
								</l>
							</v>
						</tfr>
					</token>
					<token id="1398800" text="сказал">
						<tfr rev_id="3050688" t="сказал">
							<v>
								<l id="321532" t="сказал">
									<g v="VERB"/>
									<g v="perf"/>
									<g v="tran"/>
									<g v="masc"/>
									<g v="sing"/>
									<g v="past"/>
									<g v="indc"/>
								</l>
							</v>
						</tfr>
					</token>
					<token id="1398801" text="Уайт">
						<tfr rev_id="3050689" t="Уайт">
							<v>
								<l id="352827" t="уайт">
									<g v="NOUN"/>
									<g v="anim"/>
									<g v="masc"/>
									<g v="Name"/>
									<g v="sing"/>
									<g v="nomn"/>
								</l>
							</v>
						</tfr>
					</token>
					<token id="1398802" text=",">
						<tfr rev_id="3050690" t=",">
							<v>
								<l id="0" t=",">
									<g v="PNCT"/>
								</l>
							</v>
						</tfr>
					</token>
					<token id="1398803" text="который">
						<tfr rev_id="3638036" t="который">
							<v>
								<l id="141203" t="который">
									<g v="ADJF"/>
									<g v="Apro"/>
									<g v="Subx"/>
									<g v="Anph"/>
									<g v="masc"/>
									<g v="sing"/>
									<g v="nomn"/>
								</l>
							</v>
							<v>
								<l id="141203" t="который">
									<g v="ADJF"/>
									<g v="Apro"/>
									<g v="Subx"/>
									<g v="Anph"/>
									<g v="inan"/>
									<g v="masc"/>
									<g v="sing"/>
									<g v="accs"/>
								</l>
							</v>
						</tfr>
					</token>
					<token id="1398804" text="до">
						<tfr rev_id="3050692" t="до">
							<v>
								<l id="85153" t="до">
									<g v="PREP"/>
								</l>
							</v>
						</tfr>
					</token>
					<token id="1398805" text="мая">
						<tfr rev_id="4496730" t="мая">
							<v>
								<l id="153142" t="май">
									<g v="NOUN"/>
									<g v="inan"/>
									<g v="masc"/>
									<g v="Sgtm"/>
									<g v="sing"/>
									<g v="gent"/>
								</l>
							</v>
						</tfr>
					</token>
					<token id="1398806" text="2005">
						<tfr rev_id="3050694" t="2005">
							<v>
								<l id="0" t="2005">
									<g v="NUMB"/>
								</l>
							</v>
						</tfr>
					</token>
					<token id="1398807" text="года">
						<tfr rev_id="3711966" t="года">
							<v>
								<l id="72149" t="год">
									<g v="NOUN"/>
									<g v="inan"/>
									<g v="masc"/>
									<g v="sing"/>
									<g v="gen1"/>
								</l>
							</v>
						</tfr>
					</token>
					<token id="1398808" text="работал">
						<tfr rev_id="3050696" t="работал">
							<v>
								<l id="290502" t="работаю">
									<g v="VERB"/>
									<g v="impf"/>
									<g v="intr"/>
									<g v="masc"/>
									<g v="sing"/>
									<g v="past"/>
									<g v="indc"/>
								</l>
							</v>
						</tfr>
					</token>
					<token id="1398809" text="в">
						<tfr rev_id="3050697" t="в">
							<v>
								<l id="37409" t="в">
									<g v="PREP"/>
								</l>
							</v>
						</tfr>
					</token>
					<token id="1398810" text="министерстве">
						<tfr rev_id="3050698" t="министерстве">
							<v>
								<l id="160612" t="министерство">
									<g v="NOUN"/>
									<g v="inan"/>
									<g v="neut"/>
									<g v="sing"/>
									<g v="loct"/>
								</l>
							</v>
						</tfr>
					</token>
					<token id="1398811" text="иностранных">
						<tfr rev_id="4401323" t="иностранных">
							<v>
								<l id="122754" t="иностранный">
									<g v="ADJF"/>
									<g v="plur"/>
									<g v="gent"/>
								</l>
							</v>
						</tfr>
					</token>
					<token id="1398812" text="дел">
						<tfr rev_id="3456052" t="дел">
							<v>
								<l id="80628" t="дело">
									<g v="NOUN"/>
									<g v="inan"/>
									<g v="neut"/>
									<g v="plur"/>
									<g v="gent"/>
								</l>
							</v>
						</tfr>
					</token>
					<token id="1398813" text="США">
						<tfr rev_id="3811758" t="США">
							<v>
								<l id="341371" t="сша">
									<g v="NOUN"/>
									<g v="inan"/>
									<g v="GNdr"/>
									<g v="Pltm"/>
									<g v="Fixd"/>
									<g v="Abbr"/>
									<g v="Geox"/>
									<g v="plur"/>
									<g v="nomn"/>
								</l>
							</v>
							<v>
								<l id="341371" t="сша">
									<g v="NOUN"/>
									<g v="inan"/>
									<g v="GNdr"/>
									<g v="Pltm"/>
									<g v="Fixd"/>
									<g v="Abbr"/>
									<g v="Geox"/>
									<g v="plur"/>
									<g v="gent"/>
								</l>
							</v>
							<v>
								<l id="341371" t="сша">
									<g v="NOUN"/>
									<g v="inan"/>
									<g v="GNdr"/>
									<g v="Pltm"/>
									<g v="Fixd"/>
									<g v="Abbr"/>
									<g v="Geox"/>
									<g v="plur"/>
									<g v="datv"/>
								</l>
							</v>
							<v>
								<l id="341371" t="сша">
									<g v="NOUN"/>
									<g v="inan"/>
									<g v="GNdr"/>
									<g v="Pltm"/>
									<g v="Fixd"/>
									<g v="Abbr"/>
									<g v="Geox"/>
									<g v="plur"/>
									<g v="accs"/>
								</l>
							</v>
							<v>
								<l id="341371" t="сша">
									<g v="NOUN"/>
									<g v="inan"/>
									<g v="GNdr"/>
									<g v="Pltm"/>
									<g v="Fixd"/>
									<g v="Abbr"/>
									<g v="Geox"/>
									<g v="plur"/>
									<g v="ablt"/>
								</l>
							</v>
							<v>
								<l id="341371" t="сша">
									<g v="NOUN"/>
									<g v="inan"/>
									<g v="GNdr"/>
									<g v="Pltm"/>
									<g v="Fixd"/>
									<g v="Abbr"/>
									<g v="Geox"/>
									<g v="plur"/>
									<g v="loct"/>
								</l>
							</v>
						</tfr>
					</token>
					<token id="1398814" text=".">
						<tfr rev_id="3050702" t=".">
							<v>
								<l id="0" t=".">
									<g v="PNCT"/>
								</l>
							</v>
						</tfr>
					</token>
				</tokens>
			</sentence>
			<sentence id="77852">
				<source>«Мы говорим о том, чтобы нейтрализовать иранские военно-воздушные силы, подводные лодки и ракеты, которые могут быть использованы против гражданских и военных судов США в Персидском заливе», говорит Уайт.</source>
				<tokens>
					<token id="1398815" text="«">
						<tfr rev_id="3050703" t="«">
							<v>
								<l id="0" t="«">
									<g v="PNCT"/>
								</l>
							</v>
						</tfr>
					</token>
					<token id="1398816" text="Мы">
						<tfr rev_id="3050704" t="Мы">
							<v>
								<l id="165750" t="мы">
									<g v="NPRO"/>
									<g v="1per"/>
									<g v="plur"/>
									<g v="nomn"/>
								</l>
							</v>
						</tfr>
					</token>
					<token id="1398817" text="говорим">
						<tfr rev_id="3703985" t="говорим">
							<v>
								<l id="72053" t="говорю">
									<g v="VERB"/>
									<g v="impf"/>
									<g v="tran"/>
									<g v="plur"/>
									<g v="1per"/>
									<g v="pres"/>
									<g v="indc"/>
								</l>
							</v>
						</tfr>
					</token>
					<token id="1398818" text="о">
						<tfr rev_id="3397392" t="о">
							<v>
								<l id="192977" t="о">
									<g v="PREP"/>
								</l>
							</v>
						</tfr>
					</token>
					<token id="1398819" text="том">
						<tfr rev_id="4392574" t="том">
							<v>
								<l id="348430" t="тот">
									<g v="ADJF"/>
									<g v="Subx"/>
									<g v="Apro"/>
									<g v="Anph"/>
									<g v="neut"/>
									<g v="sing"/>
									<g v="loct"/>
								</l>
							</v>
						</tfr>
					</token>
					<token id="1398820" text=",">
						<tfr rev_id="3050708" t=",">
							<v>
								<l id="0" t=",">
									<g v="PNCT"/>
								</l>
							</v>
						</tfr>
					</token>
					<token id="1398821" text="чтобы">
						<tfr rev_id="3050709" t="чтобы">
							<v>
								<l id="377013" t="чтобы">
									<g v="CONJ"/>
								</l>
							</v>
							<v>
								<l id="377014" t="чтобы">
									<g v="PRCL"/>
								</l>
							</v>
						</tfr>
					</token>
					<token id="1398822" text="нейтрализовать">
						<tfr rev_id="3050710" t="нейтрализовать">
							<v>
								<l id="183137" t="нейтрализовать">
									<g v="INFN"/>
									<g v="perf"/>
									<g v="tran"/>
								</l>
							</v>
							<v>
								<l id="183138" t="нейтрализовать">
									<g v="INFN"/>
									<g v="impf"/>
									<g v="tran"/>
								</l>
							</v>
						</tfr>
					</token>
					<token id="1398823" text="иранские">
						<tfr rev_id="3050711" t="иранские">
							<v>
								<l id="123920" t="иранский">
									<g v="ADJF"/>
									<g v="plur"/>
									<g v="nomn"/>
								</l>
							</v>
							<v>
								<l id="123920" t="иранский">
									<g v="ADJF"/>
									<g v="inan"/>
									<g v="plur"/>
									<g v="accs"/>
								</l>
							</v>
						</tfr>
					</token>
					<token id="1398824" text="военно-воздушные">
						<tfr rev_id="3050712" t="военно-воздушные">
							<v>
								<l id="48581" t="военно-воздушный">
									<g v="ADJF"/>
									<g v="plur"/>
									<g v="nomn"/>
								</l>
							</v>
							<v>
								<l id="48581" t="военно-воздушный">
									<g v="ADJF"/>
									<g v="inan"/>
									<g v="plur"/>
									<g v="accs"/>
								</l>
							</v>
						</tfr>
					</token>
					<token id="1398825" text="силы">
						<tfr rev_id="3822153" t="силы">
							<v>
								<l id="320333" t="сила">
									<g v="NOUN"/>
									<g v="inan"/>
									<g v="femn"/>
									<g v="plur"/>
									<g v="accs"/>
								</l>
							</v>
						</tfr>
					</token>
					<token id="1398826" text=",">
						<tfr rev_id="3050714" t=",">
							<v>
								<l id="0" t=",">
									<g v="PNCT"/>
								</l>
							</v>
						</tfr>
					</token>
					<token id="1398827" text="подводные">
						<tfr rev_id="3050715" t="подводные">
							<v>
								<l id="244650" t="подводной">
									<g v="ADJF"/>
									<g v="plur"/>
									<g v="nomn"/>
								</l>
							</v>
							<v>
								<l id="244650" t="подводной">
									<g v="ADJF"/>
									<g v="inan"/>
									<g v="plur"/>
									<g v="accs"/>
								</l>
							</v>
							<v>
								<l id="244652" t="подводный">
									<g v="ADJF"/>
									<g v="Qual"/>
									<g v="plur"/>
									<g v="nomn"/>
								</l>
							</v>
							<v>
								<l id="244652" t="подводный">
									<g v="ADJF"/>
									<g v="Qual"/>
									<g v="inan"/>
									<g v="plur"/>
									<g v="accs"/>
								</l>
							</v>
						</tfr>
					</token>
					<token id="1398828" text="лодки">
						<tfr rev_id="3822154" t="лодки">
							<v>
								<l id="150495" t="лодка">
									<g v="NOUN"/>
									<g v="inan"/>
									<g v="femn"/>
									<g v="plur"/>
									<g v="accs"/>
								</l>
							</v>
						</tfr>
					</token>
					<token id="1398829" text="и">
						<tfr rev_id="3050717" t="и">
							<v>
								<l id="116949" t="и">
									<g v="CONJ"/>
								</l>
							</v>
							<v>
								<l id="116950" t="и">
									<g v="INTJ"/>
								</l>
							</v>
						</tfr>
					</token>
					<token id="1398830" text="ракеты">
						<tfr rev_id="4182031" t="ракеты">
							<v>
								<l id="297650" t="ракета">
									<g v="NOUN"/>
									<g v="inan"/>
									<g v="femn"/>
									<g v="plur"/>
									<g v="accs"/>
								</l>
							</v>
						</tfr>
					</token>
					<token id="1398831" text=",">
						<tfr rev_id="3050719" t=",">
							<v>
								<l id="0" t=",">
									<g v="PNCT"/>
								</l>
							</v>
						</tfr>
					</token>
					<token id="1398832" text="которые">
						<tfr rev_id="3643239" t="которые">
							<v>
								<l id="141203" t="который">
									<g v="ADJF"/>
									<g v="Apro"/>
									<g v="Subx"/>
									<g v="Anph"/>
									<g v="plur"/>
									<g v="nomn"/>
								</l>
							</v>
							<v>
								<l id="141203" t="который">
									<g v="ADJF"/>
									<g v="Apro"/>
									<g v="Subx"/>
									<g v="Anph"/>
									<g v="inan"/>
									<g v="plur"/>
									<g v="accs"/>
								</l>
							</v>
						</tfr>
					</token>
					<token id="1398833" text="могут">
						<tfr rev_id="3050721" t="могут">
							<v>
								<l id="164485" t="могу">
									<g v="VERB"/>
									<g v="impf"/>
									<g v="intr"/>
									<g v="plur"/>
									<g v="3per"/>
									<g v="pres"/>
									<g v="indc"/>
								</l>
							</v>
						</tfr>
					</token>
					<token id="1398834" text="быть">
						<tfr rev_id="3050722" t="быть">
							<v>
								<l id="37266" t="быть">
									<g v="INFN"/>
									<g v="impf"/>
									<g v="intr"/>
								</l>
							</v>
						</tfr>
					</token>
					<token id="1398835" text="использованы">
						<tfr rev_id="3050723" t="использованы">
							<v>
								<l id="125429" t="использован">
									<g v="PRTS"/>
									<g v="perf"/>
									<g v="past"/>
									<g v="pssv"/>
									<g v="plur"/>
								</l>
							</v>
							<v>
								<l id="125430" t="использован">
									<g v="PRTS"/>
									<g v="impf"/>
									<g v="past"/>
									<g v="pssv"/>
									<g v="plur"/>
								</l>
							</v>
						</tfr>
					</token>
					<token id="1398836" text="против">
						<tfr rev_id="4485378" t="против">
							<v>
								<l id="285790" t="против">
									<g v="PREP"/>
								</l>
							</v>
						</tfr>
					</token>
					<token id="1398837" text="гражданских">
						<tfr rev_id="4409683" t="гражданских">
							<v>
								<l id="74529" t="гражданский">
									<g v="ADJF"/>
									<g v="plur"/>
									<g v="gent"/>
								</l>
							</v>
						</tfr>
					</token>
					<token id="1398838" text="и">
						<tfr rev_id="3050726" t="и">
							<v>
								<l id="116949" t="и">
									<g v="CONJ"/>
								</l>
							</v>
							<v>
								<l id="116950" t="и">
									<g v="INTJ"/>
								</l>
							</v>
						</tfr>
					</token>
					<token id="1398839" text="военных">
						<tfr rev_id="4494262" t="военных">
							<v>
								<l id="48619" t="военный">
									<g v="ADJF"/>
									<g v="plur"/>
									<g v="gent"/>
								</l>
							</v>
						</tfr>
					</token>
					<token id="1398840" text="судов">
						<tfr rev_id="3723465" t="судов">
							<v>
								<l id="339014" t="судно">
									<g v="NOUN"/>
									<g v="inan"/>
									<g v="neut"/>
									<g v="plur"/>
									<g v="gent"/>
								</l>
							</v>
						</tfr>
					</token>
					<token id="1398841" text="США">
						<tfr rev_id="3811759" t="США">
							<v>
								<l id="341371" t="сша">
									<g v="NOUN"/>
									<g v="inan"/>
									<g v="GNdr"/>
									<g v="Pltm"/>
									<g v="Fixd"/>
									<g v="Abbr"/>
									<g v="Geox"/>
									<g v="plur"/>
									<g v="nomn"/>
								</l>
							</v>
							<v>
								<l id="341371" t="сша">
									<g v="NOUN"/>
									<g v="inan"/>
									<g v="GNdr"/>
									<g v="Pltm"/>
									<g v="Fixd"/>
									<g v="Abbr"/>
									<g v="Geox"/>
									<g v="plur"/>
									<g v="gent"/>
								</l>
							</v>
							<v>
								<l id="341371" t="сша">
									<g v="NOUN"/>
									<g v="inan"/>
									<g v="GNdr"/>
									<g v="Pltm"/>
									<g v="Fixd"/>
									<g v="Abbr"/>
									<g v="Geox"/>
									<g v="plur"/>
									<g v="datv"/>
								</l>
							</v>
							<v>
								<l id="341371" t="сша">
									<g v="NOUN"/>
									<g v="inan"/>
									<g v="GNdr"/>
									<g v="Pltm"/>
									<g v="Fixd"/>
									<g v="Abbr"/>
									<g v="Geox"/>
									<g v="plur"/>
									<g v="accs"/>
								</l>
							</v>
							<v>
								<l id="341371" t="сша">
									<g v="NOUN"/>
									<g v="inan"/>
									<g v="GNdr"/>
									<g v="Pltm"/>
									<g v="Fixd"/>
									<g v="Abbr"/>
									<g v="Geox"/>
									<g v="plur"/>
									<g v="ablt"/>
								</l>
							</v>
							<v>
								<l id="341371" t="сша">
									<g v="NOUN"/>
									<g v="inan"/>
									<g v="GNdr"/>
									<g v="Pltm"/>
									<g v="Fixd"/>
									<g v="Abbr"/>
									<g v="Geox"/>
									<g v="plur"/>
									<g v="loct"/>
								</l>
							</v>
						</tfr>
					</token>
					<token id="1398842" text="в">
						<tfr rev_id="3050730" t="в">
							<v>
								<l id="37409" t="в">
									<g v="PREP"/>
								</l>
							</v>
						</tfr>
					</token>
					<token id="1398843" text="Персидском">
						<tfr rev_id="4350730" t="Персидском">
							<v>
								<l id="237434" t="персидский">
									<g v="ADJF"/>
									<g v="masc"/>
									<g v="sing"/>
									<g v="loct"/>
								</l>
							</v>
						</tfr>
					</token>
					<token id="1398844" text="заливе">
						<tfr rev_id="3050732" t="заливе">
							<v>
								<l id="104721" t="залив">
									<g v="NOUN"/>
									<g v="inan"/>
									<g v="masc"/>
									<g v="sing"/>
									<g v="loct"/>
								</l>
							</v>
						</tfr>
					</token>
					<token id="1398845" text="»">
						<tfr rev_id="3050733" t="»">
							<v>
								<l id="0" t="»">
									<g v="PNCT"/>
								</l>
							</v>
						</tfr>
					</token>
					<token id="1398846" text=",">
						<tfr rev_id="3050734" t=",">
							<v>
								<l id="0" t=",">
									<g v="PNCT"/>
								</l>
							</v>
						</tfr>
					</token>
					<token id="1398847" text="говорит">
						<tfr rev_id="3050735" t="говорит">
							<v>
								<l id="72053" t="говорю">
									<g v="VERB"/>
									<g v="impf"/>
									<g v="tran"/>
									<g v="sing"/>
									<g v="3per"/>
									<g v="pres"/>
									<g v="indc"/>
								</l>
							</v>
						</tfr>
					</token>
					<token id="1398848" text="Уайт">
						<tfr rev_id="3050736" t="Уайт">
							<v>
								<l id="352827" t="уайт">
									<g v="NOUN"/>
									<g v="anim"/>
									<g v="masc"/>
									<g v="Name"/>
									<g v="sing"/>
									<g v="nomn"/>
								</l>
							</v>
						</tfr>
					</token>
					<token id="1398849" text=".">
						<tfr rev_id="3050737" t=".">
							<v>
								<l id="0" t=".">
									<g v="PNCT"/>
								</l>
							</v>
						</tfr>
					</token>
				</tokens>
			</sentence>
		</paragraph>
		<paragraph id="26791">
			<sentence id="77853">
				<source>Президент США Джордж Буш, однако, повторяет, что он намерен найти дипломатическое решение в споре об иранской атомной программе, но военное решение проблемы — не исключено.</source>
				<tokens>
					<token id="1398850" text="Президент">
						<tfr rev_id="3050738" t="Президент">
							<v>
								<l id="267449" t="президент">
									<g v="NOUN"/>
									<g v="anim"/>
									<g v="masc"/>
									<g v="sing"/>
									<g v="nomn"/>
								</l>
							</v>
						</tfr>
					</token>
					<token id="1398851" text="США">
						<tfr rev_id="3811760" t="США">
							<v>
								<l id="341371" t="сша">
									<g v="NOUN"/>
									<g v="inan"/>
									<g v="GNdr"/>
									<g v="Pltm"/>
									<g v="Fixd"/>
									<g v="Abbr"/>
									<g v="Geox"/>
									<g v="plur"/>
									<g v="nomn"/>
								</l>
							</v>
							<v>
								<l id="341371" t="сша">
									<g v="NOUN"/>
									<g v="inan"/>
									<g v="GNdr"/>
									<g v="Pltm"/>
									<g v="Fixd"/>
									<g v="Abbr"/>
									<g v="Geox"/>
									<g v="plur"/>
									<g v="gent"/>
								</l>
							</v>
							<v>
								<l id="341371" t="сша">
									<g v="NOUN"/>
									<g v="inan"/>
									<g v="GNdr"/>
									<g v="Pltm"/>
									<g v="Fixd"/>
									<g v="Abbr"/>
									<g v="Geox"/>
									<g v="plur"/>
									<g v="datv"/>
								</l>
							</v>
							<v>
								<l id="341371" t="сша">
									<g v="NOUN"/>
									<g v="inan"/>
									<g v="GNdr"/>
									<g v="Pltm"/>
									<g v="Fixd"/>
									<g v="Abbr"/>
									<g v="Geox"/>
									<g v="plur"/>
									<g v="accs"/>
								</l>
							</v>
							<v>
								<l id="341371" t="сша">
									<g v="NOUN"/>
									<g v="inan"/>
									<g v="GNdr"/>
									<g v="Pltm"/>
									<g v="Fixd"/>
									<g v="Abbr"/>
									<g v="Geox"/>
									<g v="plur"/>
									<g v="ablt"/>
								</l>
							</v>
							<v>
								<l id="341371" t="сша">
									<g v="NOUN"/>
									<g v="inan"/>
									<g v="GNdr"/>
									<g v="Pltm"/>
									<g v="Fixd"/>
									<g v="Abbr"/>
									<g v="Geox"/>
									<g v="plur"/>
									<g v="loct"/>
								</l>
							</v>
						</tfr>
					</token>
					<token id="1398852" text="Джордж">
						<tfr rev_id="3050740" t="Джордж">
							<v>
								<l id="83107" t="джордж">
									<g v="NOUN"/>
									<g v="anim"/>
									<g v="masc"/>
									<g v="Name"/>
									<g v="sing"/>
									<g v="nomn"/>
								</l>
							</v>
						</tfr>
					</token>
					<token id="1398853" text="Буш">
						<tfr rev_id="4290820" t="Буш">
							<v>
								<l id="36908" t="буш">
									<g v="NOUN"/>
									<g v="anim"/>
									<g v="masc"/>
									<g v="Sgtm"/>
									<g v="Surn"/>
									<g v="sing"/>
									<g v="nomn"/>
								</l>
							</v>
						</tfr>
					</token>
					<token id="1398854" text=",">
						<tfr rev_id="3050742" t=",">
							<v>
								<l id="0" t=",">
									<g v="PNCT"/>
								</l>
							</v>
						</tfr>
					</token>
					<token id="1398855" text="однако">
						<tfr rev_id="3050743" t="однако">
							<v>
								<l id="203386" t="однако">
									<g v="INTJ"/>
								</l>
							</v>
							<v>
								<l id="203387" t="однако">
									<g v="CONJ"/>
									<g v="Prnt"/>
								</l>
							</v>
						</tfr>
					</token>
					<token id="1398856" text=",">
						<tfr rev_id="3050744" t=",">
							<v>
								<l id="0" t=",">
									<g v="PNCT"/>
								</l>
							</v>
						</tfr>
					</token>
					<token id="1398857" text="повторяет">
						<tfr rev_id="3050745" t="повторяет">
							<v>
								<l id="242820" t="повторяю">
									<g v="VERB"/>
									<g v="impf"/>
									<g v="tran"/>
									<g v="sing"/>
									<g v="3per"/>
									<g v="pres"/>
									<g v="indc"/>
								</l>
							</v>
						</tfr>
					</token>
					<token id="1398858" text=",">
						<tfr rev_id="3050746" t=",">
							<v>
								<l id="0" t=",">
									<g v="PNCT"/>
								</l>
							</v>
						</tfr>
					</token>
					<token id="1398859" text="что">
						<tfr rev_id="3050747" t="что">
							<v>
								<l id="377004" t="что">
									<g v="CONJ"/>
								</l>
							</v>
							<v>
								<l id="377005" t="что">
									<g v="NPRO"/>
									<g v="neut"/>
									<g v="sing"/>
									<g v="nomn"/>
								</l>
							</v>
							<v>
								<l id="377005" t="что">
									<g v="NPRO"/>
									<g v="neut"/>
									<g v="sing"/>
									<g v="accs"/>
								</l>
							</v>
							<v>
								<l id="377006" t="что">
									<g v="ADVB"/>
									<g v="Ques"/>
								</l>
							</v>
							<v>
								<l id="388695" t="что">
									<g v="PRCL"/>
								</l>
							</v>
						</tfr>
					</token>
					<token id="1398860" text="он">
						<tfr rev_id="3577651" t="он">
							<v>
								<l id="206541" t="он">
									<g v="NPRO"/>
									<g v="masc"/>
									<g v="3per"/>
									<g v="Anph"/>
									<g v="sing"/>
									<g v="nomn"/>
								</l>
							</v>
						</tfr>
					</token>
					<token id="1398861" text="намерен">
						<tfr rev_id="3050749" t="намерен">
							<v>
								<l id="172445" t="намерен">
									<g v="ADJS"/>
									<g v="masc"/>
									<g v="sing"/>
								</l>
							</v>
							<v>
								<l id="172450" t="намерен">
									<g v="ADJS"/>
									<g v="Qual"/>
									<g v="masc"/>
									<g v="sing"/>
								</l>
							</v>
							<v>
								<l id="172473" t="намерен">
									<g v="PRTS"/>
									<g v="perf"/>
									<g v="past"/>
									<g v="pssv"/>
									<g v="masc"/>
									<g v="sing"/>
								</l>
							</v>
						</tfr>
					</token>
					<token id="1398862" text="найти">
						<tfr rev_id="3050750" t="найти">
							<v>
								<l id="170612" t="найти">
									<g v="INFN"/>
									<g v="perf"/>
									<g v="tran"/>
								</l>
							</v>
						</tfr>
					</token>
					<token id="1398863" text="дипломатическое">
						<tfr rev_id="3050751" t="дипломатическое">
							<v>
								<l id="84144" t="дипломатический">
									<g v="ADJF"/>
									<g v="neut"/>
									<g v="sing"/>
									<g v="nomn"/>
								</l>
							</v>
							<v>
								<l id="84144" t="дипломатический">
									<g v="ADJF"/>
									<g v="neut"/>
									<g v="sing"/>
									<g v="accs"/>
								</l>
							</v>
						</tfr>
					</token>
					<token id="1398864" text="решение">
						<tfr rev_id="3859981" t="решение">
							<v>
								<l id="307350" t="решение">
									<g v="NOUN"/>
									<g v="inan"/>
									<g v="neut"/>
									<g v="sing"/>
									<g v="accs"/>
								</l>
							</v>
						</tfr>
					</token>
					<token id="1398865" text="в">
						<tfr rev_id="3050753" t="в">
							<v>
								<l id="37409" t="в">
									<g v="PREP"/>
								</l>
							</v>
						</tfr>
					</token>
					<token id="1398866" text="споре">
						<tfr rev_id="4082604" t="споре">
							<v>
								<l id="332735" t="спор">
									<g v="NOUN"/>
									<g v="inan"/>
									<g v="masc"/>
									<g v="sing"/>
									<g v="loct"/>
								</l>
							</v>
						</tfr>
					</token>
					<token id="1398867" text="об">
						<tfr rev_id="3050755" t="об">
							<v>
								<l id="192977" t="о">
									<g v="PREP"/>
									<g v="Vpre"/>
								</l>
							</v>
						</tfr>
					</token>
					<token id="1398868" text="иранской">
						<tfr rev_id="4345247" t="иранской">
							<v>
								<l id="123920" t="иранский">
									<g v="ADJF"/>
									<g v="femn"/>
									<g v="sing"/>
									<g v="loct"/>
								</l>
							</v>
						</tfr>
					</token>
					<token id="1398869" text="атомной">
						<tfr rev_id="4298727" t="атомной">
							<v>
								<l id="19606" t="атомный">
									<g v="ADJF"/>
									<g v="Qual"/>
									<g v="femn"/>
									<g v="sing"/>
									<g v="loct"/>
								</l>
							</v>
						</tfr>
					</token>
					<token id="1398870" text="программе">
						<tfr rev_id="3666473" t="программе">
							<v>
								<l id="278686" t="программа">
									<g v="NOUN"/>
									<g v="inan"/>
									<g v="femn"/>
									<g v="sing"/>
									<g v="loct"/>
								</l>
							</v>
						</tfr>
					</token>
					<token id="1398871" text=",">
						<tfr rev_id="3050759" t=",">
							<v>
								<l id="0" t=",">
									<g v="PNCT"/>
								</l>
							</v>
						</tfr>
					</token>
					<token id="1398872" text="но">
						<tfr rev_id="3050760" t="но">
							<v>
								<l id="191429" t="но">
									<g v="CONJ"/>
								</l>
							</v>
							<v>
								<l id="191430" t="но">
									<g v="INTJ"/>
								</l>
							</v>
						</tfr>
					</token>
					<token id="1398873" text="военное">
						<tfr rev_id="4494134" t="военное">
							<v>
								<l id="48619" t="военный">
									<g v="ADJF"/>
									<g v="neut"/>
									<g v="sing"/>
									<g v="nomn"/>
								</l>
							</v>
							<v>
								<l id="48619" t="военный">
									<g v="ADJF"/>
									<g v="neut"/>
									<g v="sing"/>
									<g v="accs"/>
								</l>
							</v>
						</tfr>
					</token>
					<token id="1398874" text="решение">
						<tfr rev_id="3050762" t="решение">
							<v>
								<l id="307350" t="решение">
									<g v="NOUN"/>
									<g v="inan"/>
									<g v="neut"/>
									<g v="sing"/>
									<g v="nomn"/>
								</l>
							</v>
							<v>
								<l id="307350" t="решение">
									<g v="NOUN"/>
									<g v="inan"/>
									<g v="neut"/>
									<g v="sing"/>
									<g v="accs"/>
								</l>
							</v>
						</tfr>
					</token>
					<token id="1398875" text="проблемы">
						<tfr rev_id="3803253" t="проблемы">
							<v>
								<l id="277255" t="проблема">
									<g v="NOUN"/>
									<g v="inan"/>
									<g v="femn"/>
									<g v="sing"/>
									<g v="gent"/>
								</l>
							</v>
						</tfr>
					</token>
					<token id="1398876" text="—">
						<tfr rev_id="3050764" t="—">
							<v>
								<l id="0" t="—">
									<g v="PNCT"/>
								</l>
							</v>
						</tfr>
					</token>
					<token id="1398877" text="не">
						<tfr rev_id="3050765" t="не">
							<v>
								<l id="178876" t="не">
									<g v="PRCL"/>
								</l>
							</v>
						</tfr>
					</token>
					<token id="1398878" text="исключено">
						<tfr rev_id="3050766" t="исключено">
							<v>
								<l id="124368" t="исключён">
									<g v="PRTS"/>
									<g v="perf"/>
									<g v="past"/>
									<g v="pssv"/>
									<g v="neut"/>
									<g v="sing"/>
								</l>
							</v>
						</tfr>
					</token>
					<token id="1398879" text=".">
						<tfr rev_id="3050767" t=".">
							<v>
								<l id="0" t=".">
									<g v="PNCT"/>
								</l>
							</v>
						</tfr>
					</token>
				</tokens>
			</sentence>
			<sentence id="77854">
				<source>Последние действия США против поддержки, которую оказывает Иран антиамериканским силам в Ираке, говорят об ужесточении американской позиции в отношении Ирана.</source>
				<tokens>
					<token id="1398880" text="Последние">
						<tfr rev_id="3050768" t="Последние">
							<v>
								<l id="261565" t="последний">
									<g v="ADJF"/>
									<g v="plur"/>
									<g v="nomn"/>
								</l>
							</v>
							<v>
								<l id="261565" t="последний">
									<g v="ADJF"/>
									<g v="inan"/>
									<g v="plur"/>
									<g v="accs"/>
								</l>
							</v>
						</tfr>
					</token>
					<token id="1398881" text="действия">
						<tfr rev_id="4206185" t="действия">
							<v>
								<l id="80091" t="действие">
									<g v="NOUN"/>
									<g v="inan"/>
									<g v="neut"/>
									<g v="plur"/>
									<g v="nomn"/>
								</l>
							</v>
						</tfr>
					</token>
					<token id="1398882" text="США">
						<tfr rev_id="3811761" t="США">
							<v>
								<l id="341371" t="сша">
									<g v="NOUN"/>
									<g v="inan"/>
									<g v="GNdr"/>
									<g v="Pltm"/>
									<g v="Fixd"/>
									<g v="Abbr"/>
									<g v="Geox"/>
									<g v="plur"/>
									<g v="nomn"/>
								</l>
							</v>
							<v>
								<l id="341371" t="сша">
									<g v="NOUN"/>
									<g v="inan"/>
									<g v="GNdr"/>
									<g v="Pltm"/>
									<g v="Fixd"/>
									<g v="Abbr"/>
									<g v="Geox"/>
									<g v="plur"/>
									<g v="gent"/>
								</l>
							</v>
							<v>
								<l id="341371" t="сша">
									<g v="NOUN"/>
									<g v="inan"/>
									<g v="GNdr"/>
									<g v="Pltm"/>
									<g v="Fixd"/>
									<g v="Abbr"/>
									<g v="Geox"/>
									<g v="plur"/>
									<g v="datv"/>
								</l>
							</v>
							<v>
								<l id="341371" t="сша">
									<g v="NOUN"/>
									<g v="inan"/>
									<g v="GNdr"/>
									<g v="Pltm"/>
									<g v="Fixd"/>
									<g v="Abbr"/>
									<g v="Geox"/>
									<g v="plur"/>
									<g v="accs"/>
								</l>
							</v>
							<v>
								<l id="341371" t="сша">
									<g v="NOUN"/>
									<g v="inan"/>
									<g v="GNdr"/>
									<g v="Pltm"/>
									<g v="Fixd"/>
									<g v="Abbr"/>
									<g v="Geox"/>
									<g v="plur"/>
									<g v="ablt"/>
								</l>
							</v>
							<v>
								<l id="341371" t="сша">
									<g v="NOUN"/>
									<g v="inan"/>
									<g v="GNdr"/>
									<g v="Pltm"/>
									<g v="Fixd"/>
									<g v="Abbr"/>
									<g v="Geox"/>
									<g v="plur"/>
									<g v="loct"/>
								</l>
							</v>
						</tfr>
					</token>
					<token id="1398883" text="против">
						<tfr rev_id="4485347" t="против">
							<v>
								<l id="285790" t="против">
									<g v="PREP"/>
								</l>
							</v>
						</tfr>
					</token>
					<token id="1398884" text="поддержки">
						<tfr rev_id="3946108" t="поддержки">
							<v>
								<l id="245415" t="поддержка">
									<g v="NOUN"/>
									<g v="inan"/>
									<g v="femn"/>
									<g v="sing"/>
									<g v="gent"/>
								</l>
							</v>
						</tfr>
					</token>
					<token id="1398885" text=",">
						<tfr rev_id="3050773" t=",">
							<v>
								<l id="0" t=",">
									<g v="PNCT"/>
								</l>
							</v>
						</tfr>
					</token>
					<token id="1398886" text="которую">
						<tfr rev_id="3641184" t="которую">
							<v>
								<l id="141203" t="который">
									<g v="ADJF"/>
									<g v="Apro"/>
									<g v="Subx"/>
									<g v="Anph"/>
									<g v="femn"/>
									<g v="sing"/>
									<g v="accs"/>
								</l>
							</v>
						</tfr>
					</token>
					<token id="1398887" text="оказывает">
						<tfr rev_id="3050775" t="оказывает">
							<v>
								<l id="204467" t="оказываю">
									<g v="VERB"/>
									<g v="impf"/>
									<g v="tran"/>
									<g v="sing"/>
									<g v="3per"/>
									<g v="pres"/>
									<g v="indc"/>
								</l>
							</v>
						</tfr>
					</token>
					<token id="1398888" text="Иран">
						<tfr rev_id="3666196" t="Иран">
							<v>
								<l id="123907" t="иран">
									<g v="NOUN"/>
									<g v="inan"/>
									<g v="masc"/>
									<g v="Geox"/>
									<g v="sing"/>
									<g v="nomn"/>
								</l>
							</v>
						</tfr>
					</token>
					<token id="1398889" text="антиамериканским">
						<tfr rev_id="3689502" t="антиамериканским">
							<v>
								<l id="14122" t="антиамериканский">
									<g v="ADJF"/>
									<g v="plur"/>
									<g v="datv"/>
								</l>
							</v>
						</tfr>
					</token>
					<token id="1398890" text="силам">
						<tfr rev_id="3050778" t="силам">
							<v>
								<l id="320333" t="сила">
									<g v="NOUN"/>
									<g v="inan"/>
									<g v="femn"/>
									<g v="plur"/>
									<g v="datv"/>
								</l>
							</v>
						</tfr>
					</token>
					<token id="1398891" text="в">
						<tfr rev_id="3050779" t="в">
							<v>
								<l id="37409" t="в">
									<g v="PREP"/>
								</l>
							</v>
						</tfr>
					</token>
					<token id="1398892" text="Ираке">
						<tfr rev_id="3050780" t="Ираке">
							<v>
								<l id="123896" t="ирак">
									<g v="NOUN"/>
									<g v="inan"/>
									<g v="masc"/>
									<g v="Geox"/>
									<g v="sing"/>
									<g v="loct"/>
								</l>
							</v>
						</tfr>
					</token>
					<token id="1398893" text=",">
						<tfr rev_id="3050781" t=",">
							<v>
								<l id="0" t=",">
									<g v="PNCT"/>
								</l>
							</v>
						</tfr>
					</token>
					<token id="1398894" text="говорят">
						<tfr rev_id="4212335" t="говорят">
							<v>
								<l id="72053" t="говорю">
									<g v="VERB"/>
									<g v="impf"/>
									<g v="tran"/>
									<g v="plur"/>
									<g v="3per"/>
									<g v="pres"/>
									<g v="indc"/>
								</l>
							</v>
						</tfr>
					</token>
					<token id="1398895" text="об">
						<tfr rev_id="3050783" t="об">
							<v>
								<l id="192977" t="о">
									<g v="PREP"/>
									<g v="Vpre"/>
								</l>
							</v>
						</tfr>
					</token>
					<token id="1398896" text="ужесточении">
						<tfr rev_id="3050784" t="ужесточении">
							<v>
								<l id="355514" t="ужесточение">
									<g v="NOUN"/>
									<g v="inan"/>
									<g v="neut"/>
									<g v="sing"/>
									<g v="loct"/>
								</l>
							</v>
						</tfr>
					</token>
					<token id="1398897" text="американской">
						<tfr rev_id="4417980" t="американской">
							<v>
								<l id="11429" t="американский">
									<g v="ADJF"/>
									<g v="femn"/>
									<g v="sing"/>
									<g v="gent"/>
								</l>
							</v>
						</tfr>
					</token>
					<token id="1398898" text="позиции">
						<tfr rev_id="4377235" t="позиции">
							<v>
								<l id="253607" t="позиция">
									<g v="NOUN"/>
									<g v="inan"/>
									<g v="femn"/>
									<g v="sing"/>
									<g v="gent"/>
								</l>
							</v>
						</tfr>
					</token>
					<token id="1398899" text="в">
						<tfr rev_id="3050787" t="в">
							<v>
								<l id="37409" t="в">
									<g v="PREP"/>
								</l>
							</v>
						</tfr>
					</token>
					<token id="1398900" text="отношении">
						<tfr rev_id="3050788" t="отношении">
							<v>
								<l id="215944" t="отношение">
									<g v="NOUN"/>
									<g v="inan"/>
									<g v="neut"/>
									<g v="sing"/>
									<g v="loct"/>
								</l>
							</v>
						</tfr>
					</token>
					<token id="1398901" text="Ирана">
						<tfr rev_id="3050789" t="Ирана">
							<v>
								<l id="123907" t="иран">
									<g v="NOUN"/>
									<g v="inan"/>
									<g v="masc"/>
									<g v="Geox"/>
									<g v="sing"/>
									<g v="gent"/>
								</l>
							</v>
						</tfr>
					</token>
					<token id="1398902" text=".">
						<tfr rev_id="3050790" t=".">
							<v>
								<l id="0" t=".">
									<g v="PNCT"/>
								</l>
							</v>
						</tfr>
					</token>
				</tokens>
			</sentence>
		</paragraph>
		<paragraph id="26792">
			<sentence id="77855">
				<source>США считают, что под видом развития мирной атомной энергетики, Иран тайно работает над созданием атомного оружия.</source>
				<tokens>
					<token id="1398903" text="США">
						<tfr rev_id="3811762" t="США">
							<v>
								<l id="341371" t="сша">
									<g v="NOUN"/>
									<g v="inan"/>
									<g v="GNdr"/>
									<g v="Pltm"/>
									<g v="Fixd"/>
									<g v="Abbr"/>
									<g v="Geox"/>
									<g v="plur"/>
									<g v="nomn"/>
								</l>
							</v>
							<v>
								<l id="341371" t="сша">
									<g v="NOUN"/>
									<g v="inan"/>
									<g v="GNdr"/>
									<g v="Pltm"/>
									<g v="Fixd"/>
									<g v="Abbr"/>
									<g v="Geox"/>
									<g v="plur"/>
									<g v="gent"/>
								</l>
							</v>
							<v>
								<l id="341371" t="сша">
									<g v="NOUN"/>
									<g v="inan"/>
									<g v="GNdr"/>
									<g v="Pltm"/>
									<g v="Fixd"/>
									<g v="Abbr"/>
									<g v="Geox"/>
									<g v="plur"/>
									<g v="datv"/>
								</l>
							</v>
							<v>
								<l id="341371" t="сша">
									<g v="NOUN"/>
									<g v="inan"/>
									<g v="GNdr"/>
									<g v="Pltm"/>
									<g v="Fixd"/>
									<g v="Abbr"/>
									<g v="Geox"/>
									<g v="plur"/>
									<g v="accs"/>
								</l>
							</v>
							<v>
								<l id="341371" t="сша">
									<g v="NOUN"/>
									<g v="inan"/>
									<g v="GNdr"/>
									<g v="Pltm"/>
									<g v="Fixd"/>
									<g v="Abbr"/>
									<g v="Geox"/>
									<g v="plur"/>
									<g v="ablt"/>
								</l>
							</v>
							<v>
								<l id="341371" t="сша">
									<g v="NOUN"/>
									<g v="inan"/>
									<g v="GNdr"/>
									<g v="Pltm"/>
									<g v="Fixd"/>
									<g v="Abbr"/>
									<g v="Geox"/>
									<g v="plur"/>
									<g v="loct"/>
								</l>
							</v>
						</tfr>
					</token>
					<token id="1398904" text="считают">
						<tfr rev_id="3050792" t="считают">
							<v>
								<l id="341320" t="считаю">
									<g v="VERB"/>
									<g v="impf"/>
									<g v="tran"/>
									<g v="plur"/>
									<g v="3per"/>
									<g v="pres"/>
									<g v="indc"/>
								</l>
							</v>
							<v>
								<l id="341329" t="считал">
									<g v="VERB"/>
									<g v="perf"/>
									<g v="tran"/>
									<g v="plur"/>
									<g v="3per"/>
									<g v="futr"/>
									<g v="indc"/>
								</l>
							</v>
						</tfr>
					</token>
					<token id="1398905" text=",">
						<tfr rev_id="3050793" t=",">
							<v>
								<l id="0" t=",">
									<g v="PNCT"/>
								</l>
							</v>
						</tfr>
					</token>
					<token id="1398906" text="что">
						<tfr rev_id="3050794" t="что">
							<v>
								<l id="377004" t="что">
									<g v="CONJ"/>
								</l>
							</v>
							<v>
								<l id="377005" t="что">
									<g v="NPRO"/>
									<g v="neut"/>
									<g v="sing"/>
									<g v="nomn"/>
								</l>
							</v>
							<v>
								<l id="377005" t="что">
									<g v="NPRO"/>
									<g v="neut"/>
									<g v="sing"/>
									<g v="accs"/>
								</l>
							</v>
							<v>
								<l id="377006" t="что">
									<g v="ADVB"/>
									<g v="Ques"/>
								</l>
							</v>
							<v>
								<l id="388695" t="что">
									<g v="PRCL"/>
								</l>
							</v>
						</tfr>
					</token>
					<token id="1398907" text="под">
						<tfr rev_id="3339460" t="под">
							<v>
								<l id="243755" t="под">
									<g v="PREP"/>
								</l>
							</v>
						</tfr>
					</token>
					<token id="1398908" text="видом">
						<tfr rev_id="3050796" t="видом">
							<v>
								<l id="44437" t="вид">
									<g v="NOUN"/>
									<g v="inan"/>
									<g v="masc"/>
									<g v="sing"/>
									<g v="ablt"/>
								</l>
							</v>
						</tfr>
					</token>
					<token id="1398909" text="развития">
						<tfr rev_id="3801139" t="развития">
							<v>
								<l id="292545" t="развитие">
									<g v="NOUN"/>
									<g v="inan"/>
									<g v="neut"/>
									<g v="sing"/>
									<g v="gent"/>
								</l>
							</v>
						</tfr>
					</token>
					<token id="1398910" text="мирной">
						<tfr rev_id="3050798" t="мирной">
							<v>
								<l id="160883" t="мирный">
									<g v="ADJF"/>
									<g v="Qual"/>
									<g v="femn"/>
									<g v="sing"/>
									<g v="gent"/>
								</l>
							</v>
							<v>
								<l id="160883" t="мирный">
									<g v="ADJF"/>
									<g v="Qual"/>
									<g v="femn"/>
									<g v="sing"/>
									<g v="datv"/>
								</l>
							</v>
							<v>
								<l id="160883" t="мирный">
									<g v="ADJF"/>
									<g v="Qual"/>
									<g v="femn"/>
									<g v="sing"/>
									<g v="ablt"/>
								</l>
							</v>
							<v>
								<l id="160883" t="мирный">
									<g v="ADJF"/>
									<g v="Qual"/>
									<g v="femn"/>
									<g v="sing"/>
									<g v="loct"/>
								</l>
							</v>
						</tfr>
					</token>
					<token id="1398911" text="атомной">
						<tfr rev_id="4314516" t="атомной">
							<v>
								<l id="19606" t="атомный">
									<g v="ADJF"/>
									<g v="Qual"/>
									<g v="femn"/>
									<g v="sing"/>
									<g v="gent"/>
								</l>
							</v>
						</tfr>
					</token>
					<token id="1398912" text="энергетики">
						<tfr rev_id="3785947" t="энергетики">
							<v>
								<l id="385493" t="энергетика">
									<g v="NOUN"/>
									<g v="inan"/>
									<g v="femn"/>
									<g v="sing"/>
									<g v="gent"/>
								</l>
							</v>
						</tfr>
					</token>
					<token id="1398913" text=",">
						<tfr rev_id="3050801" t=",">
							<v>
								<l id="0" t=",">
									<g v="PNCT"/>
								</l>
							</v>
						</tfr>
					</token>
					<token id="1398914" text="Иран">
						<tfr rev_id="3050802" t="Иран">
							<v>
								<l id="123907" t="иран">
									<g v="NOUN"/>
									<g v="inan"/>
									<g v="masc"/>
									<g v="Geox"/>
									<g v="sing"/>
									<g v="nomn"/>
								</l>
							</v>
							<v>
								<l id="123907" t="иран">
									<g v="NOUN"/>
									<g v="inan"/>
									<g v="masc"/>
									<g v="Geox"/>
									<g v="sing"/>
									<g v="accs"/>
								</l>
							</v>
						</tfr>
					</token>
					<token id="1398915" text="тайно">
						<tfr rev_id="3050803" t="тайно">
							<v>
								<l id="342420" t="тайно">
									<g v="ADVB"/>
								</l>
							</v>
							<v>
								<l id="342433" t="таен">
									<g v="ADJS"/>
									<g v="neut"/>
									<g v="sing"/>
								</l>
							</v>
						</tfr>
					</token>
					<token id="1398916" text="работает">
						<tfr rev_id="3050804" t="работает">
							<v>
								<l id="290502" t="работаю">
									<g v="VERB"/>
									<g v="impf"/>
									<g v="intr"/>
									<g v="sing"/>
									<g v="3per"/>
									<g v="pres"/>
									<g v="indc"/>
								</l>
							</v>
						</tfr>
					</token>
					<token id="1398917" text="над">
						<tfr rev_id="3050805" t="над">
							<v>
								<l id="168356" t="над">
									<g v="PREP"/>
								</l>
							</v>
						</tfr>
					</token>
					<token id="1398918" text="созданием">
						<tfr rev_id="3050806" t="созданием">
							<v>
								<l id="328580" t="создание">
									<g v="NOUN"/>
									<g v="ANim"/>
									<g v="neut"/>
									<g v="sing"/>
									<g v="ablt"/>
								</l>
							</v>
						</tfr>
					</token>
					<token id="1398919" text="атомного">
						<tfr rev_id="4172387" t="атомного">
							<v>
								<l id="19606" t="атомный">
									<g v="ADJF"/>
									<g v="Qual"/>
									<g v="neut"/>
									<g v="sing"/>
									<g v="gent"/>
								</l>
							</v>
						</tfr>
					</token>
					<token id="1398920" text="оружия">
						<tfr rev_id="3785991" t="оружия">
							<v>
								<l id="209361" t="оружие">
									<g v="NOUN"/>
									<g v="inan"/>
									<g v="neut"/>
									<g v="sing"/>
									<g v="gent"/>
								</l>
							</v>
						</tfr>
					</token>
					<token id="1398921" text=".">
						<tfr rev_id="3050809" t=".">
							<v>
								<l id="0" t=".">
									<g v="PNCT"/>
								</l>
							</v>
						</tfr>
					</token>
				</tokens>
			</sentence>
			<sentence id="77856">
				<source>США озабочены и усиливающимся влиянием Ирана в Ираке.</source>
				<tokens>
					<token id="1398922" text="США">
						<tfr rev_id="3811763" t="США">
							<v>
								<l id="341371" t="сша">
									<g v="NOUN"/>
									<g v="inan"/>
									<g v="GNdr"/>
									<g v="Pltm"/>
									<g v="Fixd"/>
									<g v="Abbr"/>
									<g v="Geox"/>
									<g v="plur"/>
									<g v="nomn"/>
								</l>
							</v>
						</tfr>
					</token>
					<token id="1398923" text="озабочены">
						<tfr rev_id="3050811" t="озабочены">
							<v>
								<l id="203988" t="озабочен">
									<g v="PRTS"/>
									<g v="perf"/>
									<g v="past"/>
									<g v="pssv"/>
									<g v="plur"/>
								</l>
							</v>
						</tfr>
					</token>
					<token id="1398924" text="и">
						<tfr rev_id="3050812" t="и">
							<v>
								<l id="116949" t="и">
									<g v="CONJ"/>
								</l>
							</v>
							<v>
								<l id="116950" t="и">
									<g v="INTJ"/>
								</l>
							</v>
						</tfr>
					</token>
					<token id="1398925" text="усиливающимся">
						<tfr rev_id="4354664" t="усиливающимся">
							<v>
								<l id="360403" t="усиливающийся">
									<g v="PRTF"/>
									<g v="impf"/>
									<g v="intr"/>
									<g v="pres"/>
									<g v="actv"/>
									<g v="neut"/>
									<g v="sing"/>
									<g v="ablt"/>
								</l>
							</v>
						</tfr>
					</token>
					<token id="1398926" text="влиянием">
						<tfr rev_id="3050814" t="влиянием">
							<v>
								<l id="46951" t="влияние">
									<g v="NOUN"/>
									<g v="inan"/>
									<g v="neut"/>
									<g v="sing"/>
									<g v="ablt"/>
								</l>
							</v>
						</tfr>
					</token>
					<token id="1398927" text="Ирана">
						<tfr rev_id="3050815" t="Ирана">
							<v>
								<l id="123907" t="иран">
									<g v="NOUN"/>
									<g v="inan"/>
									<g v="masc"/>
									<g v="Geox"/>
									<g v="sing"/>
									<g v="gent"/>
								</l>
							</v>
						</tfr>
					</token>
					<token id="1398928" text="в">
						<tfr rev_id="3050816" t="в">
							<v>
								<l id="37409" t="в">
									<g v="PREP"/>
								</l>
							</v>
						</tfr>
					</token>
					<token id="1398929" text="Ираке">
						<tfr rev_id="3050817" t="Ираке">
							<v>
								<l id="123896" t="ирак">
									<g v="NOUN"/>
									<g v="inan"/>
									<g v="masc"/>
									<g v="Geox"/>
									<g v="sing"/>
									<g v="loct"/>
								</l>
							</v>
						</tfr>
					</token>
					<token id="1398930" text=".">
						<tfr rev_id="3050818" t=".">
							<v>
								<l id="0" t=".">
									<g v="PNCT"/>
								</l>
							</v>
						</tfr>
					</token>
				</tokens>
			</sentence>
		</paragraph>
	</paragraphs>
</text>
